[
    {
        "arm": 6,
        "seg_no": 1,
        "resolution": 360,
        "bitrate": 4481.84,
        "bitrate_ratio": 0.05139178850760383,
        "throughput": 6.986614326555405,
        "rtt": 213.78,
        "playback_buffer_ratio": 0.0,
        "rebuffering_ratio": 0.8478677423218038,
        "playback_buffer_ratio_after": 0.0,
        "rebuffering_ratio_after": 0.9938160088938299,
        "path_id": 1,
        "initial_explore": 1,
        "reward": -0.05139178850760383
    },
    {
        "arm": 5,
        "seg_no": 2,
        "resolution": 720,
        "bitrate": 22572.278,
        "bitrate_ratio": 0.25882890444791395,
        "throughput": 41.85802818523545,
        "rtt": 105.678,
        "playback_buffer_ratio": 0.2,
        "rebuffering_ratio": 0.9938160088938299,
        "playback_buffer_ratio_after": 0.2708333333333333,
        "rebuffering_ratio_after": 0.9938160088938299,
        "path_id": 1,
        "initial_explore": 1,
        "reward": 0.25882890444791395
    },
    {
        "arm": 4,
        "seg_no": 3,
        "resolution": 720,
        "bitrate": 35902.455,
        "bitrate_ratio": 0.41168166964098757,
        "throughput": 92.59532487438382,
        "rtt": 105.634,
        "playback_buffer_ratio": 0.2708333333333333,
        "rebuffering_ratio": 0.9938160088938299,
        "playback_buffer_ratio_after": 0.38333333333333336,
        "rebuffering_ratio_after": 0.3457380578012761,
        "path_id": 1,
        "initial_explore": 1,
        "reward": 0.41168166964098757
    },
    {
        "arm": 3,
        "seg_no": 4,
        "resolution": 1080,
        "bitrate": 55301.205,
        "bitrate_ratio": 0.6341207699461925,
        "throughput": 114.20629354473418,
        "rtt": 105.888,
        "playback_buffer_ratio": 0.38333333333333336,
        "rebuffering_ratio": 0.3457380578012761,
        "playback_buffer_ratio_after": 0.44166666666666665,
        "rebuffering_ratio_after": 0.3457380578012761,
        "path_id": 1,
        "initial_explore": 1,
        "reward": 0.6341207699461925
    },
    {
        "arm": 2,
        "seg_no": 5,
        "resolution": 1080,
        "bitrate": 71817.751,
        "bitrate_ratio": 0.8235105828150387,
        "throughput": 128.04850721305357,
        "rtt": 105.6,
        "playback_buffer_ratio": 0.44166666666666665,
        "rebuffering_ratio": 0.3457380578012761,
        "playback_buffer_ratio_after": 0.475,
        "rebuffering_ratio_after": 0.20925143576323602,
        "path_id": 1,
        "initial_explore": 1,
        "reward": 0.8235105828150387
    },
    {
        "arm": 1,
        "seg_no": 6,
        "resolution": 1080,
        "bitrate": 87209.263,
        "bitrate_ratio": 1.0,
        "throughput": 133.23915440993483,
        "rtt": 105.694,
        "playback_buffer_ratio": 0.475,
        "rebuffering_ratio": 0.20925143576323602,
        "playback_buffer_ratio_after": 0.48333333333333334,
        "rebuffering_ratio_after": 0.149849722514226,
        "path_id": 1,
        "initial_explore": 1,
        "reward": 1.0
    },
    {
        "arm": 12,
        "seg_no": 7,
        "resolution": 360,
        "bitrate": 4481.84,
        "bitrate_ratio": 0.05139178850760383,
        "throughput": 16.872150849015863,
        "rtt": 534.256,
        "playback_buffer_ratio": 0.48333333333333334,
        "rebuffering_ratio": 0.149849722514226,
        "playback_buffer_ratio_after": 0.5333333333333333,
        "rebuffering_ratio_after": 0.11676943118214311,
        "path_id": 2,
        "initial_explore": 1,
        "reward": 0.05139178850760383
    },
    {
        "arm": 11,
        "seg_no": 8,
        "resolution": 720,
        "bitrate": 22572.278,
        "bitrate_ratio": 0.25882890444791395,
        "throughput": 27.19730223896275,
        "rtt": 19.59,
        "playback_buffer_ratio": 0.5333333333333333,
        "rebuffering_ratio": 0.11676943118214311,
        "playback_buffer_ratio_after": 0.5166666666666667,
        "rebuffering_ratio_after": 0.09565328528787546,
        "path_id": 2,
        "initial_explore": 1,
        "reward": 0.25882890444791395
    },
    {
        "arm": 10,
        "seg_no": 9,
        "resolution": 720,
        "bitrate": 35902.455,
        "bitrate_ratio": 0.41168166964098757,
        "throughput": 27.252446789892435,
        "rtt": 19.57,
        "playback_buffer_ratio": 0.5166666666666667,
        "rebuffering_ratio": 0.09565328528787546,
        "playback_buffer_ratio_after": 0.48333333333333334,
        "rebuffering_ratio_after": 0.08100542376498428,
        "path_id": 2,
        "initial_explore": 1,
        "reward": 0.41168166964098757
    },
    {
        "arm": 9,
        "seg_no": 10,
        "resolution": 1080,
        "bitrate": 55301.205,
        "bitrate_ratio": 0.6341207699461925,
        "throughput": 27.50305058675173,
        "rtt": 19.578,
        "playback_buffer_ratio": 0.4791666666666667,
        "rebuffering_ratio": 0.08100542376498428,
        "playback_buffer_ratio_after": 0.2791666666666667,
        "rebuffering_ratio_after": 0.0620353664656711,
        "path_id": 2,
        "initial_explore": 1,
        "reward": 0.6341207699461925
    },
    {
        "arm": 8,
        "seg_no": 11,
        "resolution": 1080,
        "bitrate": 71817.751,
        "bitrate_ratio": 0.8235105828150387,
        "throughput": 27.41988955980377,
        "rtt": 19.548,
        "playback_buffer_ratio": 0.2791666666666667,
        "rebuffering_ratio": 0.0620353664656711,
        "playback_buffer_ratio_after": 0.0,
        "rebuffering_ratio_after": 0.14070078803915134,
        "path_id": 2,
        "initial_explore": 1,
        "reward": -0.8235105828150387
    },
    {
        "arm": 7,
        "seg_no": 12,
        "resolution": 1080,
        "bitrate": 87209.263,
        "bitrate_ratio": 1.0,
        "throughput": 27.75934627943411,
        "rtt": 19.39,
        "playback_buffer_ratio": 0.0,
        "rebuffering_ratio": 0.14070078803915134,
        "playback_buffer_ratio_after": 0.0,
        "rebuffering_ratio_after": 0.3063990470056124,
        "path_id": 2,
        "initial_explore": 1,
        "reward": -1.0
    },
    {
        "arm": 4,
        "seg_no": 13,
        "resolution": 720,
        "bitrate": 35902.455,
        "bitrate_ratio": 0.41168166964098757,
        "throughput": 68.23218203447315,
        "rtt": 105.552,
        "playback_buffer_ratio": 0.2,
        "rebuffering_ratio": 0.3063990470056124,
        "playback_buffer_ratio_after": 0.0,
        "rebuffering_ratio_after": 0.29016657532817397,
        "path_id": 1,
        "initial_explore": 0,
        "reward": 0.41168166964098757
    },
    {
        "arm": 4,
        "seg_no": 18,
        "resolution": 720,
        "bitrate": 35902.455,
        "bitrate_ratio": 0.41168166964098757,
        "throughput": 27.541197490056483,
        "rtt": 19.47,
        "playback_buffer_ratio": 0.3875,
        "rebuffering_ratio": 0.3063990470056124,
        "playback_buffer_ratio_after": 0.25,
        "rebuffering_ratio_after": 0.29016657532817397,
        "path_id": 2,
        "initial_explore": 0,
        "reward": 0.41168166964098757
    },
    {
        "arm": 1,
        "seg_no": 14,
        "resolution": 1080,
        "bitrate": 87209.263,
        "bitrate_ratio": 1.0,
        "throughput": 140.17710118955156,
        "rtt": 105.682,
        "playback_buffer_ratio": 0.0,
        "rebuffering_ratio": 0.29016657532817397,
        "playback_buffer_ratio_after": 0.0,
        "rebuffering_ratio_after": 0.27737720912159597,
        "path_id": 1,
        "initial_explore": 0,
        "reward": 1.0
    },
    {
        "arm": 4,
        "seg_no": 15,
        "resolution": 720,
        "bitrate": 35902.455,
        "bitrate_ratio": 0.41168166964098757,
        "throughput": 69.92860236262676,
        "rtt": 105.662,
        "playback_buffer_ratio": 0.0,
        "rebuffering_ratio": 0.27737720912159597,
        "playback_buffer_ratio_after": 0.21666666666666667,
        "rebuffering_ratio_after": 0.27737720912159597,
        "path_id": 1,
        "initial_explore": 0,
        "reward": 0.41168166964098757
    },
    {
        "arm": 4,
        "seg_no": 16,
        "resolution": 720,
        "bitrate": 35902.455,
        "bitrate_ratio": 0.41168166964098757,
        "throughput": 108.74623353406774,
        "rtt": 105.72,
        "playback_buffer_ratio": 0.21666666666666667,
        "rebuffering_ratio": 0.27737720912159597,
        "playback_buffer_ratio_after": 0.29583333333333334,
        "rebuffering_ratio_after": 0.2627907892803526,
        "path_id": 1,
        "initial_explore": 0,
        "reward": 0.41168166964098757
    },
    {
        "arm": 3,
        "seg_no": 17,
        "resolution": 1080,
        "bitrate": 55301.205,
        "bitrate_ratio": 0.6341207699461925,
        "throughput": 116.36312266816965,
        "rtt": 105.678,
        "playback_buffer_ratio": 0.49166666666666664,
        "rebuffering_ratio": 0.2627907892803526,
        "playback_buffer_ratio_after": 0.3458333333333333,
        "rebuffering_ratio_after": 0.2496237070247304,
        "path_id": 1,
        "initial_explore": 0,
        "reward": 0.6341207699461925
    },
    {
        "arm": 1,
        "seg_no": 19,
        "resolution": 1080,
        "bitrate": 87209.263,
        "bitrate_ratio": 1.0,
        "throughput": 27.667979362520793,
        "rtt": 19.566,
        "playback_buffer_ratio": 0.25,
        "rebuffering_ratio": 0.29016657532817397,
        "playback_buffer_ratio_after": 0.5458333333333333,
        "rebuffering_ratio_after": 0.23769593029269387,
        "path_id": 2,
        "initial_explore": 0,
        "reward": 1.0
    },
    {
        "arm": 1,
        "seg_no": 20,
        "resolution": 1080,
        "bitrate": 87209.263,
        "bitrate_ratio": 1.0,
        "throughput": 87.41218863492269,
        "rtt": 105.672,
        "playback_buffer_ratio": 0.3458333333333333,
        "rebuffering_ratio": 0.2496237070247304,
        "playback_buffer_ratio_after": 0.7208333333333333,
        "rebuffering_ratio_after": 0.23769593029269387,
        "path_id": 1,
        "initial_explore": 0,
        "reward": 1.0
    },
    {
        "arm": 7,
        "seg_no": 22,
        "resolution": 1080,
        "bitrate": 87209.263,
        "bitrate_ratio": 1.0,
        "throughput": 122.27970744161276,
        "rtt": 105.72,
        "playback_buffer_ratio": 0.7208333333333333,
        "rebuffering_ratio": 0.23769593029269387,
        "playback_buffer_ratio_after": 0.775,
        "rebuffering_ratio_after": 0.22684183273144537,
        "path_id": 1,
        "initial_explore": 0,
        "reward": 1.0
    },
    {
        "arm": 4,
        "seg_no": 21,
        "resolution": 720,
        "bitrate": 35902.455,
        "bitrate_ratio": 0.41168166964098757,
        "throughput": 27.386373906802415,
        "rtt": 19.608,
        "playback_buffer_ratio": 0.5458333333333333,
        "rebuffering_ratio": 0.23769593029269387,
        "playback_buffer_ratio_after": 0.6458333333333334,
        "rebuffering_ratio_after": 0.22684183273144537,
        "path_id": 2,
        "initial_explore": 0,
        "reward": 0.41168166964098757
    },
    {
        "arm": 7,
        "seg_no": 23,
        "resolution": 1080,
        "bitrate": 87209.263,
        "bitrate_ratio": 1.0,
        "throughput": 122.17066242816169,
        "rtt": 105.658,
        "playback_buffer_ratio": 0.775,
        "rebuffering_ratio": 0.22684183273144537,
        "playback_buffer_ratio_after": 1.0166666666666666,
        "rebuffering_ratio_after": 0.22684183273144537,
        "path_id": 1,
        "initial_explore": 0,
        "reward": 1.0
    },
    {
        "arm": 7,
        "seg_no": 24,
        "resolution": 1080,
        "bitrate": 87209.263,
        "bitrate_ratio": 1.0,
        "throughput": 119.27339591574841,
        "rtt": 105.752,
        "playback_buffer_ratio": 1.0166666666666666,
        "rebuffering_ratio": 0.22684183273144537,
        "playback_buffer_ratio_after": 1.0666666666666667,
        "rebuffering_ratio_after": 0.21692351651704025,
        "path_id": 1,
        "initial_explore": 0,
        "reward": 1.0
    },
    {
        "arm": 7,
        "seg_no": 28,
        "resolution": 1080,
        "bitrate": 87209.263,
        "bitrate_ratio": 1.0,
        "throughput": 27.496315998711513,
        "rtt": 19.608,
        "playback_buffer_ratio": 0.6458333333333334,
        "rebuffering_ratio": 0.22684183273144537,
        "playback_buffer_ratio_after": 0.8125,
        "rebuffering_ratio_after": 0.1994034450338398,
        "path_id": 2,
        "initial_explore": 0,
        "reward": 1.0
    },
    {
        "arm": 7,
        "seg_no": 25,
        "resolution": 1080,
        "bitrate": 87209.263,
        "bitrate_ratio": 1.0,
        "throughput": 105.55629730146131,
        "rtt": 105.662,
        "playback_buffer_ratio": 0.8,
        "rebuffering_ratio": 0.1994034450338398,
        "playback_buffer_ratio_after": 0.7833333333333333,
        "rebuffering_ratio_after": 0.19168040866257371,
        "path_id": 1,
        "initial_explore": 0,
        "reward": 1.0
    },
    {
        "arm": 7,
        "seg_no": 26,
        "resolution": 1080,
        "bitrate": 87209.263,
        "bitrate_ratio": 1.0,
        "throughput": 121.33870969773062,
        "rtt": 105.702,
        "playback_buffer_ratio": 0.7833333333333333,
        "rebuffering_ratio": 0.19168040866257371,
        "playback_buffer_ratio_after": 0.8291666666666667,
        "rebuffering_ratio_after": 0.19168040866257371,
        "path_id": 1,
        "initial_explore": 0,
        "reward": 1.0
    },
    {
        "arm": 7,
        "seg_no": 27,
        "resolution": 1080,
        "bitrate": 87209.263,
        "bitrate_ratio": 1.0,
        "throughput": 80.05111219650689,
        "rtt": 106.118,
        "playback_buffer_ratio": 0.8291666666666667,
        "rebuffering_ratio": 0.19168040866257371,
        "playback_buffer_ratio_after": 0.825,
        "rebuffering_ratio_after": 0.18452693836212355,
        "path_id": 1,
        "initial_explore": 0,
        "reward": 1.0
    },
    {
        "arm": 7,
        "seg_no": 29,
        "resolution": 1080,
        "bitrate": 87209.263,
        "bitrate_ratio": 1.0,
        "throughput": 116.01215920302585,
        "rtt": 105.744,
        "playback_buffer_ratio": 0.825,
        "rebuffering_ratio": 0.18452693836212355,
        "playback_buffer_ratio_after": 1.0916666666666666,
        "rebuffering_ratio_after": 0.17788230854430195,
        "path_id": 1,
        "initial_explore": 0,
        "reward": 1.0
    },
    {
        "arm": 7,
        "seg_no": 30,
        "resolution": 1080,
        "bitrate": 87209.263,
        "bitrate_ratio": 1.0,
        "throughput": 27.39885699549852,
        "rtt": 19.604,
        "playback_buffer_ratio": 0.8125,
        "rebuffering_ratio": 0.1994034450338398,
        "playback_buffer_ratio_after": 1.2166666666666666,
        "rebuffering_ratio_after": 0.17788230854430195,
        "path_id": 2,
        "initial_explore": 0,
        "reward": 1.0
    },
    {
        "arm": 7,
        "seg_no": 31,
        "resolution": 1080,
        "bitrate": 87209.263,
        "bitrate_ratio": 1.0,
        "throughput": 117.90520370160489,
        "rtt": 105.694,
        "playback_buffer_ratio": 1.0916666666666666,
        "rebuffering_ratio": 0.17788230854430195,
        "playback_buffer_ratio_after": 1.3416666666666666,
        "rebuffering_ratio_after": 0.17168417143670922,
        "path_id": 1,
        "initial_explore": 0,
        "reward": 1.0
    },
    {
        "arm": 7,
        "seg_no": 32,
        "resolution": 1080,
        "bitrate": 87209.263,
        "bitrate_ratio": 1.0,
        "throughput": 27.614770718818004,
        "rtt": 19.572,
        "playback_buffer_ratio": 1.2166666666666666,
        "rebuffering_ratio": 0.17788230854430195,
        "playback_buffer_ratio_after": 0.9916666666666667,
        "rebuffering_ratio_after": 0.15542930240271866,
        "path_id": 2,
        "initial_explore": 0,
        "reward": 1.0
    },
    {
        "arm": 7,
        "seg_no": 33,
        "resolution": 1080,
        "bitrate": 87209.263,
        "bitrate_ratio": 1.0,
        "throughput": 89.37537709812304,
        "rtt": 105.664,
        "playback_buffer_ratio": 0.8,
        "rebuffering_ratio": 0.15542930240271866,
        "playback_buffer_ratio_after": 1.0541666666666667,
        "rebuffering_ratio_after": 0.15542930240271866,
        "path_id": 1,
        "initial_explore": 0,
        "reward": 1.0
    },
    {
        "arm": 7,
        "seg_no": 34,
        "resolution": 1080,
        "bitrate": 87209.263,
        "bitrate_ratio": 1.0,
        "throughput": 94.21853765577312,
        "rtt": 105.562,
        "playback_buffer_ratio": 0.8,
        "rebuffering_ratio": 0.14622481220909406,
        "playback_buffer_ratio_after": 0.8083333333333333,
        "rebuffering_ratio_after": 0.14622481220909406,
        "path_id": 1,
        "initial_explore": 0,
        "reward": 1.0
    },
    {
        "arm": 7,
        "seg_no": 35,
        "resolution": 1080,
        "bitrate": 87209.263,
        "bitrate_ratio": 1.0,
        "throughput": 121.80818651735898,
        "rtt": 105.648,
        "playback_buffer_ratio": 0.8083333333333333,
        "rebuffering_ratio": 0.14622481220909406,
        "playback_buffer_ratio_after": 0.8583333333333333,
        "rebuffering_ratio_after": 0.14204204769327855,
        "path_id": 1,
        "initial_explore": 0,
        "reward": 1.0
    },
    {
        "arm": 7,
        "seg_no": 38,
        "resolution": 1080,
        "bitrate": 87209.263,
        "bitrate_ratio": 1.0,
        "throughput": 27.759168344493485,
        "rtt": 19.562,
        "playback_buffer_ratio": 0.9916666666666667,
        "rebuffering_ratio": 0.15542930240271866,
        "playback_buffer_ratio_after": 1.0333333333333334,
        "rebuffering_ratio_after": 0.14204204769327855,
        "path_id": 2,
        "initial_explore": 0,
        "reward": 1.0
    },
    {
        "arm": 7,
        "seg_no": 36,
        "resolution": 1080,
        "bitrate": 87209.263,
        "bitrate_ratio": 1.0,
        "throughput": 106.003469455448,
        "rtt": 105.736,
        "playback_buffer_ratio": 0.8583333333333333,
        "rebuffering_ratio": 0.14204204769327855,
        "playback_buffer_ratio_after": 0.9291666666666667,
        "rebuffering_ratio_after": 0.13808751825337334,
        "path_id": 1,
        "initial_explore": 0,
        "reward": 1.0
    },
    {
        "arm": 7,
        "seg_no": 37,
        "resolution": 1080,
        "bitrate": 87209.263,
        "bitrate_ratio": 1.0,
        "throughput": 109.64312344963831,
        "rtt": 105.78,
        "playback_buffer_ratio": 0.9291666666666667,
        "rebuffering_ratio": 0.13808751825337334,
        "playback_buffer_ratio_after": 0.9958333333333333,
        "rebuffering_ratio_after": 0.1343502066359686,
        "path_id": 1,
        "initial_explore": 0,
        "reward": 1.0
    },
    {
        "arm": 7,
        "seg_no": 40,
        "resolution": 1080,
        "bitrate": 87209.263,
        "bitrate_ratio": 1.0,
        "throughput": 132.17212185861487,
        "rtt": 105.772,
        "playback_buffer_ratio": 0.9958333333333333,
        "rebuffering_ratio": 0.1343502066359686,
        "playback_buffer_ratio_after": 1.2125,
        "rebuffering_ratio_after": 0.1343502066359686,
        "path_id": 1,
        "initial_explore": 0,
        "reward": 1.0
    },
    {
        "arm": 7,
        "seg_no": 41,
        "resolution": 1080,
        "bitrate": 87209.263,
        "bitrate_ratio": 1.0,
        "throughput": 87.72858961816868,
        "rtt": 105.656,
        "playback_buffer_ratio": 1.2125,
        "rebuffering_ratio": 0.1343502066359686,
        "playback_buffer_ratio_after": 0.8,
        "rebuffering_ratio_after": 0.12743164036302979,
        "path_id": 1,
        "initial_explore": 0,
        "reward": 1.0
    },
    {
        "arm": 7,
        "seg_no": 42,
        "resolution": 1080,
        "bitrate": 87209.263,
        "bitrate_ratio": 1.0,
        "throughput": 112.96107015387082,
        "rtt": 105.702,
        "playback_buffer_ratio": 0.8,
        "rebuffering_ratio": 0.12743164036302979,
        "playback_buffer_ratio_after": 0.8458333333333333,
        "rebuffering_ratio_after": 0.12743164036302979,
        "path_id": 1,
        "initial_explore": 0,
        "reward": 1.0
    },
    {
        "arm": 7,
        "seg_no": 39,
        "resolution": 1080,
        "bitrate": 87209.263,
        "bitrate_ratio": 1.0,
        "throughput": 27.810399699020703,
        "rtt": 19.68,
        "playback_buffer_ratio": 1.0333333333333334,
        "rebuffering_ratio": 0.14204204769327855,
        "playback_buffer_ratio_after": 0.7625,
        "rebuffering_ratio_after": 0.12423734368397844,
        "path_id": 2,
        "initial_explore": 0,
        "reward": 1.0
    },
    {
        "arm": 7,
        "seg_no": 43,
        "resolution": 1080,
        "bitrate": 87209.263,
        "bitrate_ratio": 1.0,
        "throughput": 70.96987299575879,
        "rtt": 105.654,
        "playback_buffer_ratio": 0.8458333333333333,
        "rebuffering_ratio": 0.12743164036302979,
        "playback_buffer_ratio_after": 1.4625,
        "rebuffering_ratio_after": 0.12423734368397844,
        "path_id": 1,
        "initial_explore": 0,
        "reward": 1.0
    },
    {
        "arm": 7,
        "seg_no": 44,
        "resolution": 1080,
        "bitrate": 87209.263,
        "bitrate_ratio": 1.0,
        "throughput": 108.44766763170311,
        "rtt": 105.69,
        "playback_buffer_ratio": 1.4625,
        "rebuffering_ratio": 0.12423734368397844,
        "playback_buffer_ratio_after": 1.5291666666666666,
        "rebuffering_ratio_after": 0.1211769113027628,
        "path_id": 1,
        "initial_explore": 0,
        "reward": 1.0
    },
    {
        "arm": 7,
        "seg_no": 45,
        "resolution": 1080,
        "bitrate": 87209.263,
        "bitrate_ratio": 1.0,
        "throughput": 27.461967179940373,
        "rtt": 19.726,
        "playback_buffer_ratio": 0.7583333333333333,
        "rebuffering_ratio": 0.12423734368397844,
        "playback_buffer_ratio_after": 1.45,
        "rebuffering_ratio_after": 0.11824230337971536,
        "path_id": 2,
        "initial_explore": 0,
        "reward": 1.0
    },
    {
        "arm": 7,
        "seg_no": 51,
        "resolution": 1080,
        "bitrate": 87209.263,
        "bitrate_ratio": 1.0,
        "throughput": 27.451863904303888,
        "rtt": 19.544,
        "playback_buffer_ratio": 1.45,
        "rebuffering_ratio": 0.11824230337971536,
        "playback_buffer_ratio_after": 1.1666666666666667,
        "rebuffering_ratio_after": 0.11028219940404956,
        "path_id": 2,
        "initial_explore": 0,
        "reward": 1.0
    },
    {
        "arm": 7,
        "seg_no": 46,
        "resolution": 1080,
        "bitrate": 87209.263,
        "bitrate_ratio": 1.0,
        "throughput": 89.04267864975245,
        "rtt": 105.622,
        "playback_buffer_ratio": 0.8,
        "rebuffering_ratio": 0.10787302991515897,
        "playback_buffer_ratio_after": 0.8291666666666667,
        "rebuffering_ratio_after": 0.10787302991515897,
        "path_id": 1,
        "initial_explore": 0,
        "reward": 1.0
    },
    {
        "arm": 7,
        "seg_no": 47,
        "resolution": 1080,
        "bitrate": 87209.263,
        "bitrate_ratio": 1.0,
        "throughput": 110.77136179580735,
        "rtt": 105.658,
        "playback_buffer_ratio": 0.8291666666666667,
        "rebuffering_ratio": 0.10787302991515897,
        "playback_buffer_ratio_after": 0.9083333333333333,
        "rebuffering_ratio_after": 0.10557580026287686,
        "path_id": 1,
        "initial_explore": 0,
        "reward": 1.0
    },
    {
        "arm": 7,
        "seg_no": 48,
        "resolution": 1080,
        "bitrate": 87209.263,
        "bitrate_ratio": 1.0,
        "throughput": 74.40773202887881,
        "rtt": 105.608,
        "playback_buffer_ratio": 0.9083333333333333,
        "rebuffering_ratio": 0.10557580026287686,
        "playback_buffer_ratio_after": 0.9166666666666666,
        "rebuffering_ratio_after": 0.10337082051976443,
        "path_id": 1,
        "initial_explore": 0,
        "reward": 1.0
    },
    {
        "arm": 7,
        "seg_no": 51,
        "resolution": 1080,
        "bitrate": 87209.263,
        "bitrate_ratio": 1.0,
        "throughput": 27.65207851247486,
        "rtt": 19.566,
        "playback_buffer_ratio": 0.9916666666666667,
        "rebuffering_ratio": 0.10787302991515897,
        "playback_buffer_ratio_after": 1.1083333333333334,
        "rebuffering_ratio_after": 0.10337082051976443,
        "path_id": 2,
        "initial_explore": 0,
        "reward": 1.0
    },
    {
        "arm": 7,
        "seg_no": 49,
        "resolution": 1080,
        "bitrate": 87209.263,
        "bitrate_ratio": 1.0,
        "throughput": 109.03458687873902,
        "rtt": 105.724,
        "playback_buffer_ratio": 0.9166666666666666,
        "rebuffering_ratio": 0.10337082051976443,
        "playback_buffer_ratio_after": 0.9875,
        "rebuffering_ratio_after": 0.10125418077353718,
        "path_id": 1,
        "initial_explore": 0,
        "reward": 1.0
    },
    {
        "arm": 7,
        "seg_no": 50,
        "resolution": 1080,
        "bitrate": 87209.263,
        "bitrate_ratio": 1.0,
        "throughput": 105.92295373373352,
        "rtt": 105.808,
        "playback_buffer_ratio": 0.9875,
        "rebuffering_ratio": 0.10125418077353718,
        "playback_buffer_ratio_after": 1.0583333333333333,
        "rebuffering_ratio_after": 0.10125418077353718,
        "path_id": 1,
        "initial_explore": 0,
        "reward": 1.0
    },
    {
        "arm": 7,
        "seg_no": 52,
        "resolution": 1080,
        "bitrate": 87209.263,
        "bitrate_ratio": 1.0,
        "throughput": 27.477207140566815,
        "rtt": 19.632,
        "playback_buffer_ratio": 1.1083333333333334,
        "rebuffering_ratio": 0.10337082051976443,
        "playback_buffer_ratio_after": 1.3416666666666666,
        "rebuffering_ratio_after": 0.0992173788951503,
        "path_id": 2,
        "initial_explore": 0,
        "reward": 1.0
    },
    {
        "arm": 7,
        "seg_no": 53,
        "resolution": 1080,
        "bitrate": 87209.263,
        "bitrate_ratio": 1.0,
        "throughput": 117.92796797703909,
        "rtt": 105.636,
        "playback_buffer_ratio": 1.0583333333333333,
        "rebuffering_ratio": 0.10125418077353718,
        "playback_buffer_ratio_after": 1.5166666666666666,
        "rebuffering_ratio_after": 0.0992173788951503,
        "path_id": 1,
        "initial_explore": 0,
        "reward": 1.0
    },
    {
        "arm": 7,
        "seg_no": 55,
        "resolution": 1080,
        "bitrate": 87209.263,
        "bitrate_ratio": 1.0,
        "throughput": 27.468638758685632,
        "rtt": 19.57,
        "playback_buffer_ratio": 1.3416666666666666,
        "rebuffering_ratio": 0.0992173788951503,
        "playback_buffer_ratio_after": 1.1541666666666666,
        "rebuffering_ratio_after": 0.09356010165653302,
        "path_id": 2,
        "initial_explore": 0,
        "reward": 1.0
    },
    {
        "arm": 7,
        "seg_no": 54,
        "resolution": 1080,
        "bitrate": 87209.263,
        "bitrate_ratio": 1.0,
        "throughput": 92.24512750069093,
        "rtt": 105.516,
        "playback_buffer_ratio": 0.8,
        "rebuffering_ratio": 0.09182154484870057,
        "playback_buffer_ratio_after": 0.8208333333333333,
        "rebuffering_ratio_after": 0.09182154484870057,
        "path_id": 1,
        "initial_explore": 0,
        "reward": 1.0
    },
    {
        "arm": 7,
        "seg_no": 56,
        "resolution": 1080,
        "bitrate": 87209.263,
        "bitrate_ratio": 1.0,
        "throughput": 115.86786890424426,
        "rtt": 105.782,
        "playback_buffer_ratio": 0.8208333333333333,
        "rebuffering_ratio": 0.09182154484870057,
        "playback_buffer_ratio_after": 1.0833333333333333,
        "rebuffering_ratio_after": 0.09014605865677547,
        "path_id": 1,
        "initial_explore": 0,
        "reward": 1.0
    },
    {
        "arm": 7,
        "seg_no": 57,
        "resolution": 1080,
        "bitrate": 87209.263,
        "bitrate_ratio": 1.0,
        "throughput": 75.25139619541557,
        "rtt": 105.85,
        "playback_buffer_ratio": 1.0833333333333333,
        "rebuffering_ratio": 0.09014605865677547,
        "playback_buffer_ratio_after": 1.0916666666666666,
        "rebuffering_ratio_after": 0.08852947865867695,
        "path_id": 1,
        "initial_explore": 0,
        "reward": 1.0
    },
    {
        "arm": 7,
        "seg_no": 59,
        "resolution": 1080,
        "bitrate": 87209.263,
        "bitrate_ratio": 1.0,
        "throughput": 27.601219678251837,
        "rtt": 19.672,
        "playback_buffer_ratio": 0.9916666666666667,
        "rebuffering_ratio": 0.09182154484870057,
        "playback_buffer_ratio_after": 1.2458333333333333,
        "rebuffering_ratio_after": 0.08852947865867695,
        "path_id": 2,
        "initial_explore": 0,
        "reward": 1.0
    },
    {
        "arm": 7,
        "seg_no": 58,
        "resolution": 1080,
        "bitrate": 87209.263,
        "bitrate_ratio": 1.0,
        "throughput": 71.46828930238887,
        "rtt": 105.664,
        "playback_buffer_ratio": 0.8,
        "rebuffering_ratio": 0.08546132606787205,
        "playback_buffer_ratio_after": 0.8291666666666667,
        "rebuffering_ratio_after": 0.08546132606787205,
        "path_id": 1,
        "initial_explore": 0,
        "reward": 1.0
    },
    {
        "arm": 7,
        "seg_no": 60,
        "resolution": 1080,
        "bitrate": 87209.263,
        "bitrate_ratio": 1.0,
        "throughput": 135.03579922766286,
        "rtt": 105.67,
        "playback_buffer_ratio": 0.8291666666666667,
        "rebuffering_ratio": 0.08546132606787205,
        "playback_buffer_ratio_after": 1.0541666666666667,
        "rebuffering_ratio_after": 0.08401104331018117,
        "path_id": 1,
        "initial_explore": 0,
        "reward": 1.0
    },
    {
        "arm": 7,
        "seg_no": 61,
        "resolution": 1080,
        "bitrate": 87209.263,
        "bitrate_ratio": 1.0,
        "throughput": 27.6295112969579,
        "rtt": 19.568,
        "playback_buffer_ratio": 1.2458333333333333,
        "rebuffering_ratio": 0.08852947865867695,
        "playback_buffer_ratio_after": 1.1708333333333334,
        "rebuffering_ratio_after": 0.08260571860139286,
        "path_id": 2,
        "initial_explore": 0,
        "reward": 1.0
    },
    {
        "arm": 7,
        "seg_no": 62,
        "resolution": 1080,
        "bitrate": 87209.263,
        "bitrate_ratio": 1.0,
        "throughput": 73.8961514108982,
        "rtt": 105.598,
        "playback_buffer_ratio": 1.0541666666666667,
        "rebuffering_ratio": 0.08401104331018117,
        "playback_buffer_ratio_after": 1.2625,
        "rebuffering_ratio_after": 0.08260571860139286,
        "path_id": 1,
        "initial_explore": 0,
        "reward": 1.0
    },
    {
        "arm": 7,
        "seg_no": 63,
        "resolution": 1080,
        "bitrate": 87209.263,
        "bitrate_ratio": 1.0,
        "throughput": 27.527767473584703,
        "rtt": 19.596,
        "playback_buffer_ratio": 1.1708333333333334,
        "rebuffering_ratio": 0.08260571860139286,
        "playback_buffer_ratio_after": 1.0333333333333334,
        "rebuffering_ratio_after": 0.07992741524308174,
        "path_id": 2,
        "initial_explore": 0,
        "reward": 1.0
    },
    {
        "arm": 7,
        "seg_no": 64,
        "resolution": 1080,
        "bitrate": 87209.263,
        "bitrate_ratio": 1.0,
        "throughput": 86.50938947943744,
        "rtt": 105.588,
        "playback_buffer_ratio": 0.8,
        "rebuffering_ratio": 0.07742589003574069,
        "playback_buffer_ratio_after": 0.825,
        "rebuffering_ratio_after": 0.07742589003574069,
        "path_id": 1,
        "initial_explore": 0,
        "reward": 1.0
    },
    {
        "arm": 7,
        "seg_no": 65,
        "resolution": 1080,
        "bitrate": 87209.263,
        "bitrate_ratio": 1.0,
        "throughput": 104.84138871930229,
        "rtt": 105.792,
        "playback_buffer_ratio": 0.825,
        "rebuffering_ratio": 0.07742589003574069,
        "playback_buffer_ratio_after": 0.9041666666666667,
        "rebuffering_ratio_after": 0.07623419591006851,
        "path_id": 1,
        "initial_explore": 0,
        "reward": 1.0
    },
    {
        "arm": 7,
        "seg_no": 66,
        "resolution": 1080,
        "bitrate": 87209.263,
        "bitrate_ratio": 1.0,
        "throughput": 105.97629685975039,
        "rtt": 105.712,
        "playback_buffer_ratio": 0.9041666666666667,
        "rebuffering_ratio": 0.07623419591006851,
        "playback_buffer_ratio_after": 0.9791666666666666,
        "rebuffering_ratio_after": 0.0750775764746649,
        "path_id": 1,
        "initial_explore": 0,
        "reward": 1.0
    },
    {
        "arm": 7,
        "seg_no": 69,
        "resolution": 1080,
        "bitrate": 87209.263,
        "bitrate_ratio": 1.0,
        "throughput": 27.71910702056961,
        "rtt": 19.618,
        "playback_buffer_ratio": 0.9916666666666667,
        "rebuffering_ratio": 0.07742589003574069,
        "playback_buffer_ratio_after": 1.1125,
        "rebuffering_ratio_after": 0.0750775764746649,
        "path_id": 2,
        "initial_explore": 0,
        "reward": 1.0
    },
    {
        "arm": 7,
        "seg_no": 67,
        "resolution": 1080,
        "bitrate": 87209.263,
        "bitrate_ratio": 1.0,
        "throughput": 71.15567855442613,
        "rtt": 105.704,
        "playback_buffer_ratio": 0.9791666666666666,
        "rebuffering_ratio": 0.0750775764746649,
        "playback_buffer_ratio_after": 0.9916666666666667,
        "rebuffering_ratio_after": 0.07395323025811484,
        "path_id": 1,
        "initial_explore": 0,
        "reward": 1.0
    },
    {
        "arm": 7,
        "seg_no": 68,
        "resolution": 1080,
        "bitrate": 87209.263,
        "bitrate_ratio": 1.0,
        "throughput": 106.77568908805428,
        "rtt": 105.698,
        "playback_buffer_ratio": 0.9916666666666667,
        "rebuffering_ratio": 0.07395323025811484,
        "playback_buffer_ratio_after": 1.0625,
        "rebuffering_ratio_after": 0.07395323025811484,
        "path_id": 1,
        "initial_explore": 0,
        "reward": 1.0
    },
    {
        "arm": 7,
        "seg_no": 71,
        "resolution": 1080,
        "bitrate": 87209.263,
        "bitrate_ratio": 1.0,
        "throughput": 110.99171254746012,
        "rtt": 105.758,
        "playback_buffer_ratio": 1.0625,
        "rebuffering_ratio": 0.07395323025811484,
        "playback_buffer_ratio_after": 1.3416666666666666,
        "rebuffering_ratio_after": 0.07286046485346316,
        "path_id": 1,
        "initial_explore": 0,
        "reward": 1.0
    },
    {
        "arm": 7,
        "seg_no": 70,
        "resolution": 1080,
        "bitrate": 87209.263,
        "bitrate_ratio": 1.0,
        "throughput": 27.36378760388054,
        "rtt": 19.602,
        "playback_buffer_ratio": 1.1125,
        "rebuffering_ratio": 0.0750775764746649,
        "playback_buffer_ratio_after": 1.2083333333333333,
        "rebuffering_ratio_after": 0.07286046485346316,
        "path_id": 2,
        "initial_explore": 0,
        "reward": 1.0
    },
    {
        "arm": 7,
        "seg_no": 76,
        "resolution": 1080,
        "bitrate": 87209.263,
        "bitrate_ratio": 1.0,
        "throughput": 27.236097491763747,
        "rtt": 19.564,
        "playback_buffer_ratio": 1.2083333333333333,
        "rebuffering_ratio": 0.07286046485346316,
        "playback_buffer_ratio_after": 1.1666666666666667,
        "rebuffering_ratio_after": 0.06977039503731511,
        "path_id": 2,
        "initial_explore": 0,
        "reward": 1.0
    },
    {
        "arm": 7,
        "seg_no": 72,
        "resolution": 1080,
        "bitrate": 87209.263,
        "bitrate_ratio": 1.0,
        "throughput": 74.42343672136012,
        "rtt": 105.592,
        "playback_buffer_ratio": 0.8,
        "rebuffering_ratio": 0.06880019326239953,
        "playback_buffer_ratio_after": 0.8041666666666667,
        "rebuffering_ratio_after": 0.06880019326239953,
        "path_id": 1,
        "initial_explore": 0,
        "reward": 1.0
    },
    {
        "arm": 7,
        "seg_no": 73,
        "resolution": 1080,
        "bitrate": 87209.263,
        "bitrate_ratio": 1.0,
        "throughput": 104.84254090317484,
        "rtt": 105.838,
        "playback_buffer_ratio": 0.8041666666666667,
        "rebuffering_ratio": 0.06880019326239953,
        "playback_buffer_ratio_after": 0.8916666666666667,
        "rebuffering_ratio_after": 0.06786039233179887,
        "path_id": 1,
        "initial_explore": 0,
        "reward": 1.0
    },
    {
        "arm": 7,
        "seg_no": 74,
        "resolution": 1080,
        "bitrate": 87209.263,
        "bitrate_ratio": 1.0,
        "throughput": 102.33542718475277,
        "rtt": 105.81,
        "playback_buffer_ratio": 0.8916666666666667,
        "rebuffering_ratio": 0.06786039233179887,
        "playback_buffer_ratio_after": 0.9916666666666667,
        "rebuffering_ratio_after": 0.06694417401622973,
        "path_id": 1,
        "initial_explore": 0,
        "reward": 1.0
    },
    {
        "arm": 7,
        "seg_no": 77,
        "resolution": 1080,
        "bitrate": 87209.263,
        "bitrate_ratio": 1.0,
        "throughput": 27.68298318352421,
        "rtt": 19.658,
        "playback_buffer_ratio": 0.9916666666666667,
        "rebuffering_ratio": 0.06880019326239953,
        "playback_buffer_ratio_after": 1.0666666666666667,
        "rebuffering_ratio_after": 0.06694417401622973,
        "path_id": 2,
        "initial_explore": 0,
        "reward": 1.0
    },
    {
        "arm": 7,
        "seg_no": 75,
        "resolution": 1080,
        "bitrate": 87209.263,
        "bitrate_ratio": 1.0,
        "throughput": 20.133380853149628,
        "rtt": 105.742,
        "playback_buffer_ratio": 0.9916666666666667,
        "rebuffering_ratio": 0.06694417401622973,
        "playback_buffer_ratio_after": 0.6541666666666667,
        "rebuffering_ratio_after": 0.06518235101845288,
        "path_id": 1,
        "initial_explore": 0,
        "reward": 1.0
    },
    {
        "arm": 7,
        "seg_no": 78,
        "resolution": 1080,
        "bitrate": 87209.263,
        "bitrate_ratio": 1.0,
        "throughput": 27.339734007690097,
        "rtt": 19.688,
        "playback_buffer_ratio": 1.0666666666666667,
        "rebuffering_ratio": 0.06694417401622973,
        "playback_buffer_ratio_after": 1.2291666666666667,
        "rebuffering_ratio_after": 0.06518235101845288,
        "path_id": 2,
        "initial_explore": 0,
        "reward": 1.0
    },
    {
        "arm": 7,
        "seg_no": 79,
        "resolution": 1080,
        "bitrate": 87209.263,
        "bitrate_ratio": 1.0,
        "throughput": 21.172441718522048,
        "rtt": 105.668,
        "playback_buffer_ratio": 0.6541666666666667,
        "rebuffering_ratio": 0.06518235101845288,
        "playback_buffer_ratio_after": 0.9291666666666667,
        "rebuffering_ratio_after": 0.06270600126393028,
        "path_id": 1,
        "initial_explore": 0,
        "reward": 1.0
    },
    {
        "arm": 7,
        "seg_no": 85,
        "resolution": 1080,
        "bitrate": 87209.263,
        "bitrate_ratio": 1.0,
        "throughput": 27.485674555471494,
        "rtt": 19.584,
        "playback_buffer_ratio": 1.2291666666666667,
        "rebuffering_ratio": 0.06518235101845288,
        "playback_buffer_ratio_after": 1.1,
        "rebuffering_ratio_after": 0.06270600126393028,
        "path_id": 2,
        "initial_explore": 0,
        "reward": 1.0
    },
    {
        "arm": 7,
        "seg_no": 80,
        "resolution": 1080,
        "bitrate": 87209.263,
        "bitrate_ratio": 1.0,
        "throughput": 23.919576341316706,
        "rtt": 105.656,
        "playback_buffer_ratio": 0.9291666666666667,
        "rebuffering_ratio": 0.06270600126393028,
        "playback_buffer_ratio_after": 0.6208333333333333,
        "rebuffering_ratio_after": 0.0611597008337622,
        "path_id": 1,
        "initial_explore": 0,
        "reward": 1.0
    },
    {
        "arm": 7,
        "seg_no": 86,
        "resolution": 1080,
        "bitrate": 87209.263,
        "bitrate_ratio": 1.0,
        "throughput": 27.463141878175477,
        "rtt": 19.558,
        "playback_buffer_ratio": 1.1,
        "rebuffering_ratio": 0.06270600126393028,
        "playback_buffer_ratio_after": 0.7833333333333333,
        "rebuffering_ratio_after": 0.060417176331914825,
        "path_id": 2,
        "initial_explore": 0,
        "reward": 1.0
    },
    {
        "arm": 7,
        "seg_no": 81,
        "resolution": 1080,
        "bitrate": 87209.263,
        "bitrate_ratio": 1.0,
        "throughput": 26.58983865942295,
        "rtt": 105.56,
        "playback_buffer_ratio": 0.6208333333333333,
        "rebuffering_ratio": 0.0611597008337622,
        "playback_buffer_ratio_after": 0.30833333333333335,
        "rebuffering_ratio_after": 0.05898756260552644,
        "path_id": 1,
        "initial_explore": 0,
        "reward": 1.0
    },
    {
        "arm": 7,
        "seg_no": 87,
        "resolution": 1080,
        "bitrate": 87209.263,
        "bitrate_ratio": 1.0,
        "throughput": 27.572115878493502,
        "rtt": 19.532,
        "playback_buffer_ratio": 0.7833333333333333,
        "rebuffering_ratio": 0.060417176331914825,
        "playback_buffer_ratio_after": 0.425,
        "rebuffering_ratio_after": 0.05898756260552644,
        "path_id": 2,
        "initial_explore": 0,
        "reward": 1.0
    },
    {
        "arm": 1,
        "seg_no": 82,
        "resolution": 1080,
        "bitrate": 87209.263,
        "bitrate_ratio": 1.0,
        "throughput": 81.0993825860357,
        "rtt": 105.768,
        "playback_buffer_ratio": 0.30833333333333335,
        "rebuffering_ratio": 0.05898756260552644,
        "playback_buffer_ratio_after": 0.30833333333333335,
        "rebuffering_ratio_after": 0.058298445094935,
        "path_id": 1,
        "initial_explore": 0,
        "reward": 1.0
    },
    {
        "arm": 1,
        "seg_no": 83,
        "resolution": 1080,
        "bitrate": 87209.263,
        "bitrate_ratio": 1.0,
        "throughput": 106.42315828435288,
        "rtt": 105.832,
        "playback_buffer_ratio": 0.30833333333333335,
        "rebuffering_ratio": 0.058298445094935,
        "playback_buffer_ratio_after": 0.38333333333333336,
        "rebuffering_ratio_after": 0.05762076913166607,
        "path_id": 1,
        "initial_explore": 0,
        "reward": 1.0
    },
    {
        "arm": 1,
        "seg_no": 84,
        "resolution": 1080,
        "bitrate": 87209.263,
        "bitrate_ratio": 1.0,
        "throughput": 80.24851817383247,
        "rtt": 105.62,
        "playback_buffer_ratio": 0.38333333333333336,
        "rebuffering_ratio": 0.05762076913166607,
        "playback_buffer_ratio_after": 0.37916666666666665,
        "rebuffering_ratio_after": 0.056962541964707944,
        "path_id": 1,
        "initial_explore": 0,
        "reward": 1.0
    },
    {
        "arm": 1,
        "seg_no": 90,
        "resolution": 1080,
        "bitrate": 87209.263,
        "bitrate_ratio": 1.0,
        "throughput": 113.42763871347485,
        "rtt": 105.786,
        "playback_buffer_ratio": 0.37916666666666665,
        "rebuffering_ratio": 0.056962541964707944,
        "playback_buffer_ratio_after": 1.0375,
        "rebuffering_ratio_after": 0.056962541964707944,
        "path_id": 1,
        "initial_explore": 0,
        "reward": 1.0
    },
    {
        "arm": 1,
        "seg_no": 88,
        "resolution": 1080,
        "bitrate": 87209.263,
        "bitrate_ratio": 1.0,
        "throughput": 27.50468176436811,
        "rtt": 19.604,
        "playback_buffer_ratio": 0.425,
        "rebuffering_ratio": 0.05898756260552644,
        "playback_buffer_ratio_after": 0.9875,
        "rebuffering_ratio_after": 0.05631604266579825,
        "path_id": 2,
        "initial_explore": 0,
        "reward": 1.0
    },
    {
        "arm": 1,
        "seg_no": 91,
        "resolution": 1080,
        "bitrate": 87209.263,
        "bitrate_ratio": 1.0,
        "throughput": 113.79275148330237,
        "rtt": 105.718,
        "playback_buffer_ratio": 1.0375,
        "rebuffering_ratio": 0.056962541964707944,
        "playback_buffer_ratio_after": 1.1,
        "rebuffering_ratio_after": 0.05631604266579825,
        "path_id": 1,
        "initial_explore": 0,
        "reward": 1.0
    },
    {
        "arm": 7,
        "seg_no": 92,
        "resolution": 1080,
        "bitrate": 87209.263,
        "bitrate_ratio": 1.0,
        "throughput": 76.8497072757405,
        "rtt": 105.616,
        "playback_buffer_ratio": 1.1,
        "rebuffering_ratio": 0.05631604266579825,
        "playback_buffer_ratio_after": 0.9041666666666667,
        "rebuffering_ratio_after": 0.055682347583948646,
        "path_id": 1,
        "initial_explore": 0,
        "reward": 1.0
    },
    {
        "arm": 7,
        "seg_no": 93,
        "resolution": 1080,
        "bitrate": 87209.263,
        "bitrate_ratio": 1.0,
        "throughput": 103.72318299147234,
        "rtt": 105.826,
        "playback_buffer_ratio": 0.9041666666666667,
        "rebuffering_ratio": 0.055682347583948646,
        "playback_buffer_ratio_after": 0.775,
        "rebuffering_ratio_after": 0.05506486572474506,
        "path_id": 1,
        "initial_explore": 0,
        "reward": 1.0
    },
    {
        "arm": 1,
        "seg_no": 89,
        "resolution": 1080,
        "bitrate": 87209.263,
        "bitrate_ratio": 1.0,
        "throughput": 27.554228719996363,
        "rtt": 19.658,
        "playback_buffer_ratio": 0.9875,
        "rebuffering_ratio": 0.05631604266579825,
        "playback_buffer_ratio_after": 0.6166666666666667,
        "rebuffering_ratio_after": 0.05506486572474506,
        "path_id": 2,
        "initial_explore": 0,
        "reward": 1.0
    },
    {
        "arm": 7,
        "seg_no": 94,
        "resolution": 1080,
        "bitrate": 87209.263,
        "bitrate_ratio": 1.0,
        "throughput": 124.17595319292585,
        "rtt": 105.724,
        "playback_buffer_ratio": 0.775,
        "rebuffering_ratio": 0.05506486572474506,
        "playback_buffer_ratio_after": 1.6125,
        "rebuffering_ratio_after": 0.05506486572474506,
        "path_id": 1,
        "initial_explore": 0,
        "reward": 1.0
    },
    {
        "arm": 7,
        "seg_no": 95,
        "resolution": 1080,
        "bitrate": 87209.263,
        "bitrate_ratio": 1.0,
        "throughput": 80.07503216183771,
        "rtt": 105.722,
        "playback_buffer_ratio": 1.6125,
        "rebuffering_ratio": 0.05506486572474506,
        "playback_buffer_ratio_after": 1.6041666666666667,
        "rebuffering_ratio_after": 0.05446100767829376,
        "path_id": 1,
        "initial_explore": 0,
        "reward": 1.0
    },
    {
        "arm": 7,
        "seg_no": 98,
        "resolution": 1080,
        "bitrate": 87209.263,
        "bitrate_ratio": 1.0,
        "throughput": 27.705236210673107,
        "rtt": 19.656,
        "playback_buffer_ratio": 0.6166666666666667,
        "rebuffering_ratio": 0.05506486572474506,
        "playback_buffer_ratio_after": 1.3208333333333333,
        "rebuffering_ratio_after": 0.05271100447701439,
        "path_id": 2,
        "initial_explore": 0,
        "reward": 1.0
    },
    {
        "arm": 7,
        "seg_no": 96,
        "resolution": 1080,
        "bitrate": 87209.263,
        "bitrate_ratio": 1.0,
        "throughput": 69.08911477351229,
        "rtt": 105.564,
        "playback_buffer_ratio": 0.8,
        "rebuffering_ratio": 0.05161015296704562,
        "playback_buffer_ratio_after": 0.8333333333333334,
        "rebuffering_ratio_after": 0.05161015296704562,
        "path_id": 1,
        "initial_explore": 0,
        "reward": 1.0
    },
    {
        "arm": 7,
        "seg_no": 101,
        "resolution": 1080,
        "bitrate": 87209.263,
        "bitrate_ratio": 1.0,
        "throughput": 27.559781388036235,
        "rtt": 19.548,
        "playback_buffer_ratio": 1.3208333333333333,
        "rebuffering_ratio": 0.05271100447701439,
        "playback_buffer_ratio_after": 0.9458333333333333,
        "rebuffering_ratio_after": 0.051078908524264395,
        "path_id": 2,
        "initial_explore": 0,
        "reward": 1.0
    },
    {
        "arm": 7,
        "seg_no": 97,
        "resolution": 1080,
        "bitrate": 87209.263,
        "bitrate_ratio": 1.0,
        "throughput": 126.88933577503296,
        "rtt": 105.66,
        "playback_buffer_ratio": 0.8333333333333334,
        "rebuffering_ratio": 0.05161015296704562,
        "playback_buffer_ratio_after": 0.8708333333333333,
        "rebuffering_ratio_after": 0.051078908524264395,
        "path_id": 1,
        "initial_explore": 0,
        "reward": 1.0
    },
    {
        "arm": 7,
        "seg_no": 99,
        "resolution": 1080,
        "bitrate": 87209.263,
        "bitrate_ratio": 1.0,
        "throughput": 82.7205606129696,
        "rtt": 105.59,
        "playback_buffer_ratio": 0.8708333333333333,
        "rebuffering_ratio": 0.051078908524264395,
        "playback_buffer_ratio_after": 1.0625,
        "rebuffering_ratio_after": 0.05055805694137079,
        "path_id": 1,
        "initial_explore": 0,
        "reward": 1.0
    },
    {
        "arm": 7,
        "seg_no": 100,
        "resolution": 1080,
        "bitrate": 87209.263,
        "bitrate_ratio": 1.0,
        "throughput": 118.52333857779936,
        "rtt": 105.748,
        "playback_buffer_ratio": 1.0625,
        "rebuffering_ratio": 0.05055805694137079,
        "playback_buffer_ratio_after": 1.1208333333333333,
        "rebuffering_ratio_after": 0.050046919694739726,
        "path_id": 1,
        "initial_explore": 0,
        "reward": 1.0
    },
    {
        "arm": 7,
        "seg_no": 101,
        "resolution": 1080,
        "bitrate": 87209.263,
        "bitrate_ratio": 1.0,
        "throughput": 27.571218807886506,
        "rtt": 19.784,
        "playback_buffer_ratio": 0.9458333333333333,
        "rebuffering_ratio": 0.051078908524264395,
        "playback_buffer_ratio_after": 1.3708333333333333,
        "rebuffering_ratio_after": 0.049545844921635135,
        "path_id": 2,
        "initial_explore": 0,
        "reward": 1.0
    },
    {
        "arm": 7,
        "seg_no": 102,
        "resolution": 1080,
        "bitrate": 87209.263,
        "bitrate_ratio": 1.0,
        "throughput": 73.6351842965162,
        "rtt": 105.69,
        "playback_buffer_ratio": 0.8,
        "rebuffering_ratio": 0.04857126680466994,
        "playback_buffer_ratio_after": 0.8083333333333333,
        "rebuffering_ratio_after": 0.04857126680466994,
        "path_id": 1,
        "initial_explore": 0,
        "reward": 1.0
    },
    {
        "arm": 7,
        "seg_no": 105,
        "resolution": 1080,
        "bitrate": 87209.263,
        "bitrate_ratio": 1.0,
        "throughput": 27.499772577807395,
        "rtt": 19.572,
        "playback_buffer_ratio": 1.3708333333333333,
        "rebuffering_ratio": 0.049545844921635135,
        "playback_buffer_ratio_after": 0.9666666666666667,
        "rebuffering_ratio_after": 0.04810098518320386,
        "path_id": 2,
        "initial_explore": 0,
        "reward": 1.0
    },
    {
        "arm": 7,
        "seg_no": 103,
        "resolution": 1080,
        "bitrate": 87209.263,
        "bitrate_ratio": 1.0,
        "throughput": 118.57027532359149,
        "rtt": 105.852,
        "playback_buffer_ratio": 0.8083333333333333,
        "rebuffering_ratio": 0.04857126680466994,
        "playback_buffer_ratio_after": 0.8875,
        "rebuffering_ratio_after": 0.04810098518320386,
        "path_id": 1,
        "initial_explore": 0,
        "reward": 1.0
    },
    {
        "arm": 7,
        "seg_no": 104,
        "resolution": 1080,
        "bitrate": 87209.263,
        "bitrate_ratio": 1.0,
        "throughput": 78.46325828520379,
        "rtt": 105.604,
        "playback_buffer_ratio": 0.8875,
        "rebuffering_ratio": 0.04810098518320386,
        "playback_buffer_ratio_after": 0.8875,
        "rebuffering_ratio_after": 0.04763538551086668,
        "path_id": 1,
        "initial_explore": 0,
        "reward": 1.0
    },
    {
        "arm": 7,
        "seg_no": 106,
        "resolution": 1080,
        "bitrate": 87209.263,
        "bitrate_ratio": 1.0,
        "throughput": 120.81140160194012,
        "rtt": 105.66,
        "playback_buffer_ratio": 0.8875,
        "rebuffering_ratio": 0.04763538551086668,
        "playback_buffer_ratio_after": 1.1416666666666666,
        "rebuffering_ratio_after": 0.04718040580016008,
        "path_id": 1,
        "initial_explore": 0,
        "reward": 1.0
    },
    {
        "arm": 7,
        "seg_no": 108,
        "resolution": 1080,
        "bitrate": 87209.263,
        "bitrate_ratio": 1.0,
        "throughput": 77.82184840322431,
        "rtt": 105.64,
        "playback_buffer_ratio": 1.1416666666666666,
        "rebuffering_ratio": 0.04718040580016008,
        "playback_buffer_ratio_after": 1.1458333333333333,
        "rebuffering_ratio_after": 0.04673484565244054,
        "path_id": 1,
        "initial_explore": 0,
        "reward": 1.0
    },
    {
        "arm": 7,
        "seg_no": 107,
        "resolution": 1080,
        "bitrate": 87209.263,
        "bitrate_ratio": 1.0,
        "throughput": 27.73263183770608,
        "rtt": 19.634,
        "playback_buffer_ratio": 0.9666666666666667,
        "rebuffering_ratio": 0.04810098518320386,
        "playback_buffer_ratio_after": 1.0458333333333334,
        "rebuffering_ratio_after": 0.04673484565244054,
        "path_id": 2,
        "initial_explore": 0,
        "reward": 1.0
    },
    {
        "arm": 7,
        "seg_no": 111,
        "resolution": 1080,
        "bitrate": 87209.263,
        "bitrate_ratio": 1.0,
        "throughput": 27.36543169577281,
        "rtt": 19.58,
        "playback_buffer_ratio": 1.0458333333333334,
        "rebuffering_ratio": 0.04673484565244054,
        "playback_buffer_ratio_after": 0.9375,
        "rebuffering_ratio_after": 0.04544549373406079,
        "path_id": 2,
        "initial_explore": 0,
        "reward": 1.0
    },
    {
        "arm": 7,
        "seg_no": 109,
        "resolution": 1080,
        "bitrate": 87209.263,
        "bitrate_ratio": 1.0,
        "throughput": 77.92825118730495,
        "rtt": 105.726,
        "playback_buffer_ratio": 0.8,
        "rebuffering_ratio": 0.04544549373406079,
        "playback_buffer_ratio_after": 0.8041666666666667,
        "rebuffering_ratio_after": 0.04544549373406079,
        "path_id": 1,
        "initial_explore": 0,
        "reward": 1.0
    },
    {
        "arm": 7,
        "seg_no": 110,
        "resolution": 1080,
        "bitrate": 87209.263,
        "bitrate_ratio": 1.0,
        "throughput": 119.24399182750022,
        "rtt": 105.818,
        "playback_buffer_ratio": 0.8041666666666667,
        "rebuffering_ratio": 0.04544549373406079,
        "playback_buffer_ratio_after": 0.8666666666666667,
        "rebuffering_ratio_after": 0.04502879618797518,
        "path_id": 1,
        "initial_explore": 0,
        "reward": 1.0
    },
    {
        "arm": 7,
        "seg_no": 112,
        "resolution": 1080,
        "bitrate": 87209.263,
        "bitrate_ratio": 1.0,
        "throughput": 105.68945091734757,
        "rtt": 107.072,
        "playback_buffer_ratio": 0.8666666666666667,
        "rebuffering_ratio": 0.04502879618797518,
        "playback_buffer_ratio_after": 1.15,
        "rebuffering_ratio_after": 0.04462190808893236,
        "path_id": 1,
        "initial_explore": 0,
        "reward": 1.0
    },
    {
        "arm": 7,
        "seg_no": 113,
        "resolution": 1080,
        "bitrate": 87209.263,
        "bitrate_ratio": 1.0,
        "throughput": 73.64023041199098,
        "rtt": 105.706,
        "playback_buffer_ratio": 1.15,
        "rebuffering_ratio": 0.04462190808893236,
        "playback_buffer_ratio_after": 1.1625,
        "rebuffering_ratio_after": 0.04422048241786803,
        "path_id": 1,
        "initial_explore": 0,
        "reward": 1.0
    },
    {
        "arm": 7,
        "seg_no": 114,
        "resolution": 1080,
        "bitrate": 87209.263,
        "bitrate_ratio": 1.0,
        "throughput": 27.09250080680726,
        "rtt": 20.024,
        "playback_buffer_ratio": 0.9375,
        "rebuffering_ratio": 0.04544549373406079,
        "playback_buffer_ratio_after": 1.2833333333333334,
        "rebuffering_ratio_after": 0.04422048241786803,
        "path_id": 2,
        "initial_explore": 0,
        "reward": 1.0
    },
    {
        "arm": 7,
        "seg_no": 117,
        "resolution": 1080,
        "bitrate": 87209.263,
        "bitrate_ratio": 1.0,
        "throughput": 26.457525586834315,
        "rtt": 20.218,
        "playback_buffer_ratio": 1.2833333333333334,
        "rebuffering_ratio": 0.04422048241786803,
        "playback_buffer_ratio_after": 0.9041666666666667,
        "rebuffering_ratio_after": 0.04305936946308031,
        "path_id": 2,
        "initial_explore": 0,
        "reward": 1.0
    },
    {
        "arm": 7,
        "seg_no": 115,
        "resolution": 1080,
        "bitrate": 87209.263,
        "bitrate_ratio": 1.0,
        "throughput": 89.59396919122416,
        "rtt": 106.296,
        "playback_buffer_ratio": 0.8,
        "rebuffering_ratio": 0.04305936946308031,
        "playback_buffer_ratio_after": 0.8083333333333333,
        "rebuffering_ratio_after": 0.04305936946308031,
        "path_id": 1,
        "initial_explore": 0,
        "reward": 1.0
    },
    {
        "arm": 7,
        "seg_no": 116,
        "resolution": 1080,
        "bitrate": 87209.263,
        "bitrate_ratio": 1.0,
        "throughput": 84.1691564107815,
        "rtt": 105.752,
        "playback_buffer_ratio": 0.8083333333333333,
        "rebuffering_ratio": 0.04305936946308031,
        "playback_buffer_ratio_after": 0.9,
        "rebuffering_ratio_after": 0.04268519264707174,
        "path_id": 1,
        "initial_explore": 0,
        "reward": 1.0
    },
    {
        "arm": 7,
        "seg_no": 118,
        "resolution": 1080,
        "bitrate": 87209.263,
        "bitrate_ratio": 1.0,
        "throughput": 101.54090649720285,
        "rtt": 105.876,
        "playback_buffer_ratio": 0.9,
        "rebuffering_ratio": 0.04268519264707174,
        "playback_buffer_ratio_after": 1.1458333333333333,
        "rebuffering_ratio_after": 0.04231723222329642,
        "path_id": 1,
        "initial_explore": 0,
        "reward": 1.0
    },
    {
        "arm": 7,
        "seg_no": 119,
        "resolution": 1080,
        "bitrate": 87209.263,
        "bitrate_ratio": 1.0,
        "throughput": 105.57366799160377,
        "rtt": 105.742,
        "playback_buffer_ratio": 1.1458333333333333,
        "rebuffering_ratio": 0.04231723222329642,
        "playback_buffer_ratio_after": 1.1875,
        "rebuffering_ratio_after": 0.041952879098552234,
        "path_id": 1,
        "initial_explore": 0,
        "reward": 1.0
    },
    {
        "arm": 7,
        "seg_no": 120,
        "resolution": 1080,
        "bitrate": 87209.263,
        "bitrate_ratio": 1.0,
        "throughput": 26.611850872421847,
        "rtt": 22.06,
        "playback_buffer_ratio": 0.9041666666666667,
        "rebuffering_ratio": 0.04305936946308031,
        "playback_buffer_ratio_after": 1.275,
        "rebuffering_ratio_after": 0.041952879098552234,
        "path_id": 2,
        "initial_explore": 0,
        "reward": 1.0
    },
    {
        "arm": 7,
        "seg_no": 121,
        "resolution": 1080,
        "bitrate": 87209.263,
        "bitrate_ratio": 1.0,
        "throughput": 91.66396933041094,
        "rtt": 105.658,
        "playback_buffer_ratio": 0.8,
        "rebuffering_ratio": 0.04089879293120837,
        "playback_buffer_ratio_after": 0.825,
        "rebuffering_ratio_after": 0.04089879293120837,
        "path_id": 1,
        "initial_explore": 0,
        "reward": 1.0
    },
    {
        "arm": 7,
        "seg_no": 123,
        "resolution": 1080,
        "bitrate": 87209.263,
        "bitrate_ratio": 1.0,
        "throughput": 27.377998752648303,
        "rtt": 19.542,
        "playback_buffer_ratio": 1.275,
        "rebuffering_ratio": 0.041952879098552234,
        "playback_buffer_ratio_after": 0.9583333333333334,
        "rebuffering_ratio_after": 0.04056352648184886,
        "path_id": 2,
        "initial_explore": 0,
        "reward": 1.0
    },
    {
        "arm": 7,
        "seg_no": 122,
        "resolution": 1080,
        "bitrate": 87209.263,
        "bitrate_ratio": 1.0,
        "throughput": 129.10128036254076,
        "rtt": 105.742,
        "playback_buffer_ratio": 0.825,
        "rebuffering_ratio": 0.04089879293120837,
        "playback_buffer_ratio_after": 0.8458333333333333,
        "rebuffering_ratio_after": 0.04056352648184886,
        "path_id": 1,
        "initial_explore": 0,
        "reward": 1.0
    },
    {
        "arm": 7,
        "seg_no": 124,
        "resolution": 1080,
        "bitrate": 87209.263,
        "bitrate_ratio": 1.0,
        "throughput": 85.79105829398245,
        "rtt": 105.688,
        "playback_buffer_ratio": 0.8458333333333333,
        "rebuffering_ratio": 0.04056352648184886,
        "playback_buffer_ratio_after": 1.0291666666666666,
        "rebuffering_ratio_after": 0.04023329343722814,
        "path_id": 1,
        "initial_explore": 0,
        "reward": 1.0
    },
    {
        "arm": 7,
        "seg_no": 125,
        "resolution": 1080,
        "bitrate": 87209.263,
        "bitrate_ratio": 1.0,
        "throughput": 118.13464980900278,
        "rtt": 105.718,
        "playback_buffer_ratio": 1.0291666666666666,
        "rebuffering_ratio": 0.04023329343722814,
        "playback_buffer_ratio_after": 1.0875,
        "rebuffering_ratio_after": 0.0399080602928725,
        "path_id": 1,
        "initial_explore": 0,
        "reward": 1.0
    },
    {
        "arm": 7,
        "seg_no": 126,
        "resolution": 1080,
        "bitrate": 87209.263,
        "bitrate_ratio": 1.0,
        "throughput": 27.5250054880604,
        "rtt": 19.602,
        "playback_buffer_ratio": 0.9583333333333334,
        "rebuffering_ratio": 0.04056352648184886,
        "playback_buffer_ratio_after": 1.1583333333333334,
        "rebuffering_ratio_after": 0.03958725169800151,
        "path_id": 2,
        "initial_explore": 0,
        "reward": 1.0
    },
    {
        "arm": 7,
        "seg_no": 127,
        "resolution": 1080,
        "bitrate": 87209.263,
        "bitrate_ratio": 1.0,
        "throughput": 95.68453719424241,
        "rtt": 105.576,
        "playback_buffer_ratio": 0.8,
        "rebuffering_ratio": 0.03896293418870231,
        "playback_buffer_ratio_after": 0.8125,
        "rebuffering_ratio_after": 0.03896293418870231,
        "path_id": 1,
        "initial_explore": 0,
        "reward": 1.0
    },
    {
        "arm": 7,
        "seg_no": 130,
        "resolution": 1080,
        "bitrate": 87209.263,
        "bitrate_ratio": 1.0,
        "throughput": 27.629743860268,
        "rtt": 19.684,
        "playback_buffer_ratio": 1.1583333333333334,
        "rebuffering_ratio": 0.03958725169800151,
        "playback_buffer_ratio_after": 0.8916666666666667,
        "rebuffering_ratio_after": 0.03865843228858942,
        "path_id": 2,
        "initial_explore": 0,
        "reward": 1.0
    },
    {
        "arm": 7,
        "seg_no": 128,
        "resolution": 1080,
        "bitrate": 87209.263,
        "bitrate_ratio": 1.0,
        "throughput": 106.06666788456737,
        "rtt": 105.618,
        "playback_buffer_ratio": 0.8125,
        "rebuffering_ratio": 0.03896293418870231,
        "playback_buffer_ratio_after": 0.8875,
        "rebuffering_ratio_after": 0.03865843228858942,
        "path_id": 1,
        "initial_explore": 0,
        "reward": 1.0
    },
    {
        "arm": 7,
        "seg_no": 129,
        "resolution": 1080,
        "bitrate": 87209.263,
        "bitrate_ratio": 1.0,
        "throughput": 115.01485534705661,
        "rtt": 105.602,
        "playback_buffer_ratio": 0.8875,
        "rebuffering_ratio": 0.03865843228858942,
        "playback_buffer_ratio_after": 0.9458333333333333,
        "rebuffering_ratio_after": 0.03835834966295107,
        "path_id": 1,
        "initial_explore": 0,
        "reward": 1.0
    },
    {
        "arm": 7,
        "seg_no": 131,
        "resolution": 1080,
        "bitrate": 87209.263,
        "bitrate_ratio": 1.0,
        "throughput": 78.07664241248524,
        "rtt": 105.686,
        "playback_buffer_ratio": 0.9458333333333333,
        "rebuffering_ratio": 0.03835834966295107,
        "playback_buffer_ratio_after": 1.15,
        "rebuffering_ratio_after": 0.03806276101999483,
        "path_id": 1,
        "initial_explore": 0,
        "reward": 1.0
    },
    {
        "arm": 7,
        "seg_no": 133,
        "resolution": 1080,
        "bitrate": 87209.263,
        "bitrate_ratio": 1.0,
        "throughput": 105.7161289827432,
        "rtt": 105.676,
        "playback_buffer_ratio": 1.15,
        "rebuffering_ratio": 0.03806276101999483,
        "playback_buffer_ratio_after": 1.2208333333333334,
        "rebuffering_ratio_after": 0.03806276101999483,
        "path_id": 1,
        "initial_explore": 0,
        "reward": 1.0
    },
    {
        "arm": 7,
        "seg_no": 132,
        "resolution": 1080,
        "bitrate": 87209.263,
        "bitrate_ratio": 1.0,
        "throughput": 27.579460316672563,
        "rtt": 19.562,
        "playback_buffer_ratio": 0.8916666666666667,
        "rebuffering_ratio": 0.03865843228858942,
        "playback_buffer_ratio_after": 1.0875,
        "rebuffering_ratio_after": 0.03777154759952663,
        "path_id": 2,
        "initial_explore": 0,
        "reward": 1.0
    },
    {
        "arm": 7,
        "seg_no": 136,
        "resolution": 1080,
        "bitrate": 87209.263,
        "bitrate_ratio": 1.0,
        "throughput": 27.533756481857232,
        "rtt": 20.57,
        "playback_buffer_ratio": 1.0875,
        "rebuffering_ratio": 0.03777154759952663,
        "playback_buffer_ratio_after": 0.8666666666666667,
        "rebuffering_ratio_after": 0.03692510466907977,
        "path_id": 2,
        "initial_explore": 0,
        "reward": 1.0
    },
    {
        "arm": 7,
        "seg_no": 134,
        "resolution": 1080,
        "bitrate": 87209.263,
        "bitrate_ratio": 1.0,
        "throughput": 75.32343299142934,
        "rtt": 105.852,
        "playback_buffer_ratio": 0.8,
        "rebuffering_ratio": 0.03692510466907977,
        "playback_buffer_ratio_after": 0.7666666666666667,
        "rebuffering_ratio_after": 0.03665210863677802,
        "path_id": 1,
        "initial_explore": 0,
        "reward": 1.0
    },
    {
        "arm": 7,
        "seg_no": 135,
        "resolution": 1080,
        "bitrate": 87209.263,
        "bitrate_ratio": 1.0,
        "throughput": 121.41079287950288,
        "rtt": 105.664,
        "playback_buffer_ratio": 0.7666666666666667,
        "rebuffering_ratio": 0.03665210863677802,
        "playback_buffer_ratio_after": 0.8083333333333333,
        "rebuffering_ratio_after": 0.03665210863677802,
        "path_id": 1,
        "initial_explore": 0,
        "reward": 1.0
    },
    {
        "arm": 7,
        "seg_no": 137,
        "resolution": 1080,
        "bitrate": 87209.263,
        "bitrate_ratio": 1.0,
        "throughput": 80.3865651997582,
        "rtt": 105.616,
        "playback_buffer_ratio": 0.8083333333333333,
        "rebuffering_ratio": 0.03665210863677802,
        "playback_buffer_ratio_after": 1.0041666666666667,
        "rebuffering_ratio_after": 0.03638350082630916,
        "path_id": 1,
        "initial_explore": 0,
        "reward": 1.0
    },
    {
        "arm": 7,
        "seg_no": 138,
        "resolution": 1080,
        "bitrate": 87209.263,
        "bitrate_ratio": 1.0,
        "throughput": 104.4323849633732,
        "rtt": 105.63,
        "playback_buffer_ratio": 1.0041666666666667,
        "rebuffering_ratio": 0.03638350082630916,
        "playback_buffer_ratio_after": 1.075,
        "rebuffering_ratio_after": 0.036118232525096904,
        "path_id": 1,
        "initial_explore": 0,
        "reward": 1.0
    },
    {
        "arm": 7,
        "seg_no": 139,
        "resolution": 1080,
        "bitrate": 87209.263,
        "bitrate_ratio": 1.0,
        "throughput": 27.566365239984773,
        "rtt": 19.568,
        "playback_buffer_ratio": 0.8666666666666667,
        "rebuffering_ratio": 0.03692510466907977,
        "playback_buffer_ratio_after": 1.2625,
        "rebuffering_ratio_after": 0.036118232525096904,
        "path_id": 2,
        "initial_explore": 0,
        "reward": 1.0
    },
    {
        "arm": 7,
        "seg_no": 140,
        "resolution": 1080,
        "bitrate": 87209.263,
        "bitrate_ratio": 1.0,
        "throughput": 90.90157758122452,
        "rtt": 105.544,
        "playback_buffer_ratio": 0.8,
        "rebuffering_ratio": 0.03534247169741162,
        "playback_buffer_ratio_after": 0.8291666666666667,
        "rebuffering_ratio_after": 0.03534247169741162,
        "path_id": 1,
        "initial_explore": 0,
        "reward": 1.0
    },
    {
        "arm": 7,
        "seg_no": 141,
        "resolution": 1080,
        "bitrate": 87209.263,
        "bitrate_ratio": 1.0,
        "throughput": 131.161698435357,
        "rtt": 105.716,
        "playback_buffer_ratio": 0.8291666666666667,
        "rebuffering_ratio": 0.03534247169741162,
        "playback_buffer_ratio_after": 0.8875,
        "rebuffering_ratio_after": 0.035091918559416006,
        "path_id": 1,
        "initial_explore": 0,
        "reward": 1.0
    },
    {
        "arm": 7,
        "seg_no": 142,
        "resolution": 1080,
        "bitrate": 87209.263,
        "bitrate_ratio": 1.0,
        "throughput": 27.73689268558136,
        "rtt": 19.462,
        "playback_buffer_ratio": 1.2625,
        "rebuffering_ratio": 0.036118232525096904,
        "playback_buffer_ratio_after": 1.0333333333333334,
        "rebuffering_ratio_after": 0.035091918559416006,
        "path_id": 2,
        "initial_explore": 0,
        "reward": 1.0
    },
    {
        "arm": 7,
        "seg_no": 143,
        "resolution": 1080,
        "bitrate": 87209.263,
        "bitrate_ratio": 1.0,
        "throughput": 114.97317696814078,
        "rtt": 105.686,
        "playback_buffer_ratio": 0.8875,
        "rebuffering_ratio": 0.035091918559416006,
        "playback_buffer_ratio_after": 1.15,
        "rebuffering_ratio_after": 0.03484453321211007,
        "path_id": 1,
        "initial_explore": 0,
        "reward": 1.0
    },
    {
        "arm": 7,
        "seg_no": 144,
        "resolution": 1080,
        "bitrate": 87209.263,
        "bitrate_ratio": 1.0,
        "throughput": 68.45598603054931,
        "rtt": 105.742,
        "playback_buffer_ratio": 1.15,
        "rebuffering_ratio": 0.03484453321211007,
        "playback_buffer_ratio_after": 1.1916666666666667,
        "rebuffering_ratio_after": 0.034600073166630704,
        "path_id": 1,
        "initial_explore": 0,
        "reward": 1.0
    },
    {
        "arm": 7,
        "seg_no": 145,
        "resolution": 1080,
        "bitrate": 87209.263,
        "bitrate_ratio": 1.0,
        "throughput": 27.29825297008427,
        "rtt": 19.506,
        "playback_buffer_ratio": 1.0291666666666666,
        "rebuffering_ratio": 0.035091918559416006,
        "playback_buffer_ratio_after": 1.2208333333333334,
        "rebuffering_ratio_after": 0.034600073166630704,
        "path_id": 2,
        "initial_explore": 0,
        "reward": 1.0
    },
    {
        "arm": 7,
        "seg_no": 146,
        "resolution": 1080,
        "bitrate": 87209.263,
        "bitrate_ratio": 1.0,
        "throughput": 75.29589242671322,
        "rtt": 105.62,
        "playback_buffer_ratio": 0.8,
        "rebuffering_ratio": 0.03388831864187026,
        "playback_buffer_ratio_after": 0.8583333333333333,
        "rebuffering_ratio_after": 0.03388831864187026,
        "path_id": 1,
        "initial_explore": 0,
        "reward": 1.0
    },
    {
        "arm": 7,
        "seg_no": 147,
        "resolution": 1080,
        "bitrate": 87209.263,
        "bitrate_ratio": 1.0,
        "throughput": 118.45429467780967,
        "rtt": 105.73,
        "playback_buffer_ratio": 0.8583333333333333,
        "rebuffering_ratio": 0.03388831864187026,
        "playback_buffer_ratio_after": 0.9083333333333333,
        "rebuffering_ratio_after": 0.033658726729845774,
        "path_id": 1,
        "initial_explore": 0,
        "reward": 1.0
    },
    {
        "arm": 7,
        "seg_no": 148,
        "resolution": 1080,
        "bitrate": 87209.263,
        "bitrate_ratio": 1.0,
        "throughput": 115.60335271423138,
        "rtt": 105.686,
        "playback_buffer_ratio": 0.9083333333333333,
        "rebuffering_ratio": 0.033658726729845774,
        "playback_buffer_ratio_after": 0.9666666666666667,
        "rebuffering_ratio_after": 0.0334321365967445,
        "path_id": 1,
        "initial_explore": 0,
        "reward": 1.0
    },
    {
        "arm": 7,
        "seg_no": 149,
        "resolution": 1080,
        "bitrate": 87209.263,
        "bitrate_ratio": 1.0,
        "throughput": 109.12106918587675,
        "rtt": 105.692,
        "playback_buffer_ratio": 0.9666666666666667,
        "rebuffering_ratio": 0.0334321365967445,
        "playback_buffer_ratio_after": 1.0333333333333334,
        "rebuffering_ratio_after": 0.0334321365967445,
        "path_id": 1,
        "initial_explore": 0,
        "reward": 1.0
    },
    {
        "arm": 7,
        "seg_no": 150,
        "resolution": 1080,
        "bitrate": 87209.263,
        "bitrate_ratio": 1.0,
        "throughput": 68.59570320355252,
        "rtt": 105.626,
        "playback_buffer_ratio": 1.0333333333333334,
        "rebuffering_ratio": 0.0334321365967445,
        "playback_buffer_ratio_after": 1.0666666666666667,
        "rebuffering_ratio_after": 0.03320828879110801,
        "path_id": 1,
        "initial_explore": 0,
        "reward": 1.0
    },
    {
        "arm": 7,
        "seg_no": 151,
        "resolution": 1080,
        "bitrate": 87209.263,
        "bitrate_ratio": 1.0,
        "throughput": 28.01326596270624,
        "rtt": 19.576,
        "playback_buffer_ratio": 0.9875,
        "rebuffering_ratio": 0.03388831864187026,
        "playback_buffer_ratio_after": 1.1,
        "rebuffering_ratio_after": 0.0329862783456251,
        "path_id": 2,
        "initial_explore": 0,
        "reward": 1.0
    },
    {
        "arm": 7,
        "seg_no": 153,
        "resolution": 1080,
        "bitrate": 87209.263,
        "bitrate_ratio": 1.0,
        "throughput": 84.39934542139318,
        "rtt": 107.096,
        "playback_buffer_ratio": 0.8,
        "rebuffering_ratio": 0.03255277598494308,
        "playback_buffer_ratio_after": 0.7916666666666666,
        "rebuffering_ratio_after": 0.03234081587856244,
        "path_id": 1,
        "initial_explore": 0,
        "reward": 1.0
    },
    {
        "arm": 7,
        "seg_no": 154,
        "resolution": 1080,
        "bitrate": 87209.263,
        "bitrate_ratio": 1.0,
        "throughput": 70.5905505912343,
        "rtt": 106.296,
        "playback_buffer_ratio": 0.7916666666666666,
        "rebuffering_ratio": 0.03234081587856244,
        "playback_buffer_ratio_after": 0.6041666666666666,
        "rebuffering_ratio_after": 0.03234081587856244,
        "path_id": 1,
        "initial_explore": 0,
        "reward": 1.0
    },
    {
        "arm": 7,
        "seg_no": 155,
        "resolution": 1080,
        "bitrate": 87209.263,
        "bitrate_ratio": 1.0,
        "throughput": 81.824523512524,
        "rtt": 105.682,
        "playback_buffer_ratio": 0.6041666666666666,
        "rebuffering_ratio": 0.03234081587856244,
        "playback_buffer_ratio_after": 0.44166666666666665,
        "rebuffering_ratio_after": 0.03213222066980585,
        "path_id": 1,
        "initial_explore": 0,
        "reward": 1.0
    },
    {
        "arm": 1,
        "seg_no": 156,
        "resolution": 1080,
        "bitrate": 87209.263,
        "bitrate_ratio": 1.0,
        "throughput": 114.83732189198948,
        "rtt": 105.776,
        "playback_buffer_ratio": 0.44166666666666665,
        "rebuffering_ratio": 0.03213222066980585,
        "playback_buffer_ratio_after": 0.32083333333333336,
        "rebuffering_ratio_after": 0.03192665992404393,
        "path_id": 1,
        "initial_explore": 0,
        "reward": 1.0
    },
    {
        "arm": 7,
        "seg_no": 152,
        "resolution": 1080,
        "bitrate": 87209.263,
        "bitrate_ratio": 1.0,
        "throughput": 27.81073750534291,
        "rtt": 19.492,
        "playback_buffer_ratio": 1.1,
        "rebuffering_ratio": 0.0329862783456251,
        "playback_buffer_ratio_after": 0.24583333333333332,
        "rebuffering_ratio_after": 0.03192665992404393,
        "path_id": 2,
        "initial_explore": 0,
        "reward": 1.0
    },
    {
        "arm": 1,
        "seg_no": 157,
        "resolution": 1080,
        "bitrate": 87209.263,
        "bitrate_ratio": 1.0,
        "throughput": 115.47959690478359,
        "rtt": 105.786,
        "playback_buffer_ratio": 0.32083333333333336,
        "rebuffering_ratio": 0.03192665992404393,
        "playback_buffer_ratio_after": 1.1833333333333333,
        "rebuffering_ratio_after": 0.03172237451912551,
        "path_id": 1,
        "initial_explore": 0,
        "reward": 1.0
    },
    {
        "arm": 1,
        "seg_no": 159,
        "resolution": 1080,
        "bitrate": 87209.263,
        "bitrate_ratio": 1.0,
        "throughput": 130.9468294384374,
        "rtt": 105.736,
        "playback_buffer_ratio": 1.1833333333333333,
        "rebuffering_ratio": 0.03172237451912551,
        "playback_buffer_ratio_after": 1.2458333333333333,
        "rebuffering_ratio_after": 0.03172237451912551,
        "path_id": 1,
        "initial_explore": 0,
        "reward": 1.0
    },
    {
        "arm": 7,
        "seg_no": 160,
        "resolution": 1080,
        "bitrate": 87209.263,
        "bitrate_ratio": 1.0,
        "throughput": 95.65216569905502,
        "rtt": 105.596,
        "playback_buffer_ratio": 0.8,
        "rebuffering_ratio": 0.03132092927721265,
        "playback_buffer_ratio_after": 0.8125,
        "rebuffering_ratio_after": 0.03132092927721265,
        "path_id": 1,
        "initial_explore": 0,
        "reward": 1.0
    },
    {
        "arm": 7,
        "seg_no": 158,
        "resolution": 1080,
        "bitrate": 87209.263,
        "bitrate_ratio": 1.0,
        "throughput": 27.650509594363044,
        "rtt": 19.706,
        "playback_buffer_ratio": 0.24583333333333332,
        "rebuffering_ratio": 0.03192665992404393,
        "playback_buffer_ratio_after": 0.6958333333333333,
        "rebuffering_ratio_after": 0.031124770306743835,
        "path_id": 2,
        "initial_explore": 0,
        "reward": 1.0
    },
    {
        "arm": 7,
        "seg_no": 161,
        "resolution": 1080,
        "bitrate": 87209.263,
        "bitrate_ratio": 1.0,
        "throughput": 121.79718866929655,
        "rtt": 105.664,
        "playback_buffer_ratio": 0.8125,
        "rebuffering_ratio": 0.03132092927721265,
        "playback_buffer_ratio_after": 1.2416666666666667,
        "rebuffering_ratio_after": 0.031124770306743835,
        "path_id": 1,
        "initial_explore": 0,
        "reward": 1.0
    },
    {
        "arm": 7,
        "seg_no": 162,
        "resolution": 1080,
        "bitrate": 87209.263,
        "bitrate_ratio": 1.0,
        "throughput": 79.86829372110986,
        "rtt": 105.676,
        "playback_buffer_ratio": 1.2416666666666667,
        "rebuffering_ratio": 0.031124770306743835,
        "playback_buffer_ratio_after": 1.2375,
        "rebuffering_ratio_after": 0.030930353955044683,
        "path_id": 1,
        "initial_explore": 0,
        "reward": 1.0
    },
    {
        "arm": 1,
        "seg_no": 165,
        "resolution": 1080,
        "bitrate": 87209.263,
        "bitrate_ratio": 1.0,
        "throughput": 27.692676470192463,
        "rtt": 19.654,
        "playback_buffer_ratio": 0.6958333333333333,
        "rebuffering_ratio": 0.031124770306743835,
        "playback_buffer_ratio_after": 1.0583333333333333,
        "rebuffering_ratio_after": 0.030547955707365182,
        "path_id": 2,
        "initial_explore": 0,
        "reward": 1.0
    },
    {
        "arm": 7,
        "seg_no": 163,
        "resolution": 1080,
        "bitrate": 87209.263,
        "bitrate_ratio": 1.0,
        "throughput": 92.87604914620286,
        "rtt": 105.676,
        "playback_buffer_ratio": 0.8,
        "rebuffering_ratio": 0.03036090895187068,
        "playback_buffer_ratio_after": 0.8166666666666667,
        "rebuffering_ratio_after": 0.03036090895187068,
        "path_id": 1,
        "initial_explore": 0,
        "reward": 1.0
    },
    {
        "arm": 7,
        "seg_no": 164,
        "resolution": 1080,
        "bitrate": 87209.263,
        "bitrate_ratio": 1.0,
        "throughput": 125.29920407731541,
        "rtt": 105.666,
        "playback_buffer_ratio": 0.8166666666666667,
        "rebuffering_ratio": 0.03036090895187068,
        "playback_buffer_ratio_after": 0.8541666666666666,
        "rebuffering_ratio_after": 0.030176455267858598,
        "path_id": 1,
        "initial_explore": 0,
        "reward": 1.0
    },
    {
        "arm": 7,
        "seg_no": 166,
        "resolution": 1080,
        "bitrate": 87209.263,
        "bitrate_ratio": 1.0,
        "throughput": 78.65546370064514,
        "rtt": 105.682,
        "playback_buffer_ratio": 0.8541666666666666,
        "rebuffering_ratio": 0.030176455267858598,
        "playback_buffer_ratio_after": 1.0541666666666667,
        "rebuffering_ratio_after": 0.029994104313311447,
        "path_id": 1,
        "initial_explore": 0,
        "reward": 1.0
    },
    {
        "arm": 7,
        "seg_no": 168,
        "resolution": 1080,
        "bitrate": 87209.263,
        "bitrate_ratio": 1.0,
        "throughput": 27.624850748639776,
        "rtt": 19.566,
        "playback_buffer_ratio": 1.0583333333333333,
        "rebuffering_ratio": 0.030547955707365182,
        "playback_buffer_ratio_after": 1.1958333333333333,
        "rebuffering_ratio_after": 0.029813648842750513,
        "path_id": 2,
        "initial_explore": 0,
        "reward": 1.0
    },
    {
        "arm": 7,
        "seg_no": 167,
        "resolution": 1080,
        "bitrate": 87209.263,
        "bitrate_ratio": 1.0,
        "throughput": 107.50834526068839,
        "rtt": 105.728,
        "playback_buffer_ratio": 1.0541666666666667,
        "rebuffering_ratio": 0.029994104313311447,
        "playback_buffer_ratio_after": 1.1375,
        "rebuffering_ratio_after": 0.029813648842750513,
        "path_id": 1,
        "initial_explore": 0,
        "reward": 1.0
    },
    {
        "arm": 7,
        "seg_no": 168,
        "resolution": 1080,
        "bitrate": 87209.263,
        "bitrate_ratio": 1.0,
        "throughput": 27.56405684803138,
        "rtt": 19.646,
        "playback_buffer_ratio": 1.1958333333333333,
        "rebuffering_ratio": 0.029813648842750513,
        "playback_buffer_ratio_after": 0.9333333333333333,
        "rebuffering_ratio_after": 0.02928453407582209,
        "path_id": 2,
        "initial_explore": 0,
        "reward": 1.0
    },
    {
        "arm": 7,
        "seg_no": 169,
        "resolution": 1080,
        "bitrate": 87209.263,
        "bitrate_ratio": 1.0,
        "throughput": 91.14191803706603,
        "rtt": 105.652,
        "playback_buffer_ratio": 0.8,
        "rebuffering_ratio": 0.02928453407582209,
        "playback_buffer_ratio_after": 0.8125,
        "rebuffering_ratio_after": 0.02928453407582209,
        "path_id": 1,
        "initial_explore": 0,
        "reward": 1.0
    },
    {
        "arm": 7,
        "seg_no": 170,
        "resolution": 1080,
        "bitrate": 87209.263,
        "bitrate_ratio": 1.0,
        "throughput": 109.95909969936825,
        "rtt": 105.696,
        "playback_buffer_ratio": 0.8125,
        "rebuffering_ratio": 0.02928453407582209,
        "playback_buffer_ratio_after": 0.8875,
        "rebuffering_ratio_after": 0.029112718487260172,
        "path_id": 1,
        "initial_explore": 0,
        "reward": 1.0
    },
    {
        "arm": 7,
        "seg_no": 171,
        "resolution": 1080,
        "bitrate": 87209.263,
        "bitrate_ratio": 1.0,
        "throughput": 105.18002861311209,
        "rtt": 105.716,
        "playback_buffer_ratio": 0.8875,
        "rebuffering_ratio": 0.029112718487260172,
        "playback_buffer_ratio_after": 0.9583333333333334,
        "rebuffering_ratio_after": 0.028943122312348052,
        "path_id": 1,
        "initial_explore": 0,
        "reward": 1.0
    },
    {
        "arm": 7,
        "seg_no": 172,
        "resolution": 1080,
        "bitrate": 87209.263,
        "bitrate_ratio": 1.0,
        "throughput": 84.74979701745514,
        "rtt": 105.644,
        "playback_buffer_ratio": 0.9583333333333334,
        "rebuffering_ratio": 0.028943122312348052,
        "playback_buffer_ratio_after": 0.9458333333333333,
        "rebuffering_ratio_after": 0.028775459273169074,
        "path_id": 1,
        "initial_explore": 0,
        "reward": 1.0
    },
    {
        "arm": 7,
        "seg_no": 173,
        "resolution": 1080,
        "bitrate": 87209.263,
        "bitrate_ratio": 1.0,
        "throughput": 125.35539951814592,
        "rtt": 105.652,
        "playback_buffer_ratio": 0.9458333333333333,
        "rebuffering_ratio": 0.028775459273169074,
        "playback_buffer_ratio_after": 0.9833333333333333,
        "rebuffering_ratio_after": 0.02860913564597745,
        "path_id": 1,
        "initial_explore": 0,
        "reward": 1.0
    },
    {
        "arm": 7,
        "seg_no": 174,
        "resolution": 1080,
        "bitrate": 87209.263,
        "bitrate_ratio": 1.0,
        "throughput": 27.7448296328433,
        "rtt": 19.636,
        "playback_buffer_ratio": 0.9333333333333333,
        "rebuffering_ratio": 0.02928453407582209,
        "playback_buffer_ratio_after": 1.15,
        "rebuffering_ratio_after": 0.02860913564597745,
        "path_id": 2,
        "initial_explore": 0,
        "reward": 1.0
    },
    {
        "arm": 7,
        "seg_no": 175,
        "resolution": 1080,
        "bitrate": 87209.263,
        "bitrate_ratio": 1.0,
        "throughput": 123.95641163342421,
        "rtt": 105.676,
        "playback_buffer_ratio": 0.9833333333333333,
        "rebuffering_ratio": 0.02860913564597745,
        "playback_buffer_ratio_after": 1.2208333333333334,
        "rebuffering_ratio_after": 0.02860913564597745,
        "path_id": 1,
        "initial_explore": 0,
        "reward": 1.0
    },
    {
        "arm": 7,
        "seg_no": 177,
        "resolution": 1080,
        "bitrate": 87209.263,
        "bitrate_ratio": 1.0,
        "throughput": 85.54548213284332,
        "rtt": 105.688,
        "playback_buffer_ratio": 1.2208333333333334,
        "rebuffering_ratio": 0.02860913564597745,
        "playback_buffer_ratio_after": 1.2125,
        "rebuffering_ratio_after": 0.0284447536875043,
        "path_id": 1,
        "initial_explore": 0,
        "reward": 1.0
    },
    {
        "arm": 7,
        "seg_no": 178,
        "resolution": 1080,
        "bitrate": 87209.263,
        "bitrate_ratio": 1.0,
        "throughput": 99.81358035557574,
        "rtt": 105.48,
        "playback_buffer_ratio": 0.8,
        "rebuffering_ratio": 0.02812134634154252,
        "playback_buffer_ratio_after": 0.8083333333333333,
        "rebuffering_ratio_after": 0.02812134634154252,
        "path_id": 1,
        "initial_explore": 0,
        "reward": 1.0
    },
    {
        "arm": 7,
        "seg_no": 176,
        "resolution": 1080,
        "bitrate": 87209.263,
        "bitrate_ratio": 1.0,
        "throughput": 27.675112717407934,
        "rtt": 19.572,
        "playback_buffer_ratio": 1.15,
        "rebuffering_ratio": 0.02860913564597745,
        "playback_buffer_ratio_after": 0.7458333333333333,
        "rebuffering_ratio_after": 0.027963109600147498,
        "path_id": 2,
        "initial_explore": 0,
        "reward": 1.0
    },
    {
        "arm": 7,
        "seg_no": 179,
        "resolution": 1080,
        "bitrate": 87209.263,
        "bitrate_ratio": 1.0,
        "throughput": 124.06645747869511,
        "rtt": 105.7,
        "playback_buffer_ratio": 0.8083333333333333,
        "rebuffering_ratio": 0.02812134634154252,
        "playback_buffer_ratio_after": 1.2625,
        "rebuffering_ratio_after": 0.027963109600147498,
        "path_id": 1,
        "initial_explore": 0,
        "reward": 1.0
    },
    {
        "arm": 7,
        "seg_no": 180,
        "resolution": 1080,
        "bitrate": 87209.263,
        "bitrate_ratio": 1.0,
        "throughput": 131.20755434252303,
        "rtt": 105.67,
        "playback_buffer_ratio": 1.2625,
        "rebuffering_ratio": 0.027963109600147498,
        "playback_buffer_ratio_after": 1.2875,
        "rebuffering_ratio_after": 0.0278064049963559,
        "path_id": 1,
        "initial_explore": 0,
        "reward": 1.0
    },
    {
        "arm": 7,
        "seg_no": 183,
        "resolution": 1080,
        "bitrate": 87209.263,
        "bitrate_ratio": 1.0,
        "throughput": 27.737755980933546,
        "rtt": 19.654,
        "playback_buffer_ratio": 0.7458333333333333,
        "rebuffering_ratio": 0.027963109600147498,
        "playback_buffer_ratio_after": 0.8708333333333333,
        "rebuffering_ratio_after": 0.027345570483328092,
        "path_id": 2,
        "initial_explore": 0,
        "reward": 1.0
    },
    {
        "arm": 7,
        "seg_no": 181,
        "resolution": 1080,
        "bitrate": 87209.263,
        "bitrate_ratio": 1.0,
        "throughput": 105.46715059681672,
        "rtt": 105.616,
        "playback_buffer_ratio": 0.8,
        "rebuffering_ratio": 0.027345570483328092,
        "playback_buffer_ratio_after": 0.6,
        "rebuffering_ratio_after": 0.027195954958373455,
        "path_id": 1,
        "initial_explore": 0,
        "reward": 1.0
    },
    {
        "arm": 7,
        "seg_no": 182,
        "resolution": 1080,
        "bitrate": 87209.263,
        "bitrate_ratio": 1.0,
        "throughput": 114.21725069633477,
        "rtt": 105.8,
        "playback_buffer_ratio": 0.6,
        "rebuffering_ratio": 0.027195954958373455,
        "playback_buffer_ratio_after": 0.8625,
        "rebuffering_ratio_after": 0.027195954958373455,
        "path_id": 1,
        "initial_explore": 0,
        "reward": 1.0
    },
    {
        "arm": 7,
        "seg_no": 184,
        "resolution": 1080,
        "bitrate": 87209.263,
        "bitrate_ratio": 1.0,
        "throughput": 132.71797574823017,
        "rtt": 105.642,
        "playback_buffer_ratio": 0.8625,
        "rebuffering_ratio": 0.027195954958373455,
        "playback_buffer_ratio_after": 1.0875,
        "rebuffering_ratio_after": 0.027047716185775613,
        "path_id": 1,
        "initial_explore": 0,
        "reward": 1.0
    },
    {
        "arm": 7,
        "seg_no": 185,
        "resolution": 1080,
        "bitrate": 87209.263,
        "bitrate_ratio": 1.0,
        "throughput": 130.44941884219116,
        "rtt": 105.666,
        "playback_buffer_ratio": 1.0875,
        "rebuffering_ratio": 0.027047716185775613,
        "playback_buffer_ratio_after": 1.1125,
        "rebuffering_ratio_after": 0.02690085153959439,
        "path_id": 1,
        "initial_explore": 0,
        "reward": 1.0
    },
    {
        "arm": 7,
        "seg_no": 186,
        "resolution": 1080,
        "bitrate": 87209.263,
        "bitrate_ratio": 1.0,
        "throughput": 27.58166835386638,
        "rtt": 19.574,
        "playback_buffer_ratio": 0.8708333333333333,
        "rebuffering_ratio": 0.027345570483328092,
        "playback_buffer_ratio_after": 1.275,
        "rebuffering_ratio_after": 0.02690085153959439,
        "path_id": 2,
        "initial_explore": 0,
        "reward": 1.0
    },
    {
        "arm": 7,
        "seg_no": 189,
        "resolution": 1080,
        "bitrate": 87209.263,
        "bitrate_ratio": 1.0,
        "throughput": 27.44767998467568,
        "rtt": 19.512,
        "playback_buffer_ratio": 1.275,
        "rebuffering_ratio": 0.02690085153959439,
        "playback_buffer_ratio_after": 0.9916666666666667,
        "rebuffering_ratio_after": 0.026469146448504826,
        "path_id": 2,
        "initial_explore": 0,
        "reward": 1.0
    },
    {
        "arm": 7,
        "seg_no": 187,
        "resolution": 1080,
        "bitrate": 87209.263,
        "bitrate_ratio": 1.0,
        "throughput": 89.46476873444226,
        "rtt": 105.64,
        "playback_buffer_ratio": 0.8,
        "rebuffering_ratio": 0.026469146448504826,
        "playback_buffer_ratio_after": 0.825,
        "rebuffering_ratio_after": 0.026469146448504826,
        "path_id": 1,
        "initial_explore": 0,
        "reward": 1.0
    },
    {
        "arm": 7,
        "seg_no": 188,
        "resolution": 1080,
        "bitrate": 87209.263,
        "bitrate_ratio": 1.0,
        "throughput": 117.6711520853724,
        "rtt": 105.786,
        "playback_buffer_ratio": 0.825,
        "rebuffering_ratio": 0.026469146448504826,
        "playback_buffer_ratio_after": 0.9,
        "rebuffering_ratio_after": 0.02632852251086708,
        "path_id": 1,
        "initial_explore": 0,
        "reward": 1.0
    },
    {
        "arm": 7,
        "seg_no": 190,
        "resolution": 1080,
        "bitrate": 87209.263,
        "bitrate_ratio": 1.0,
        "throughput": 105.29837389474709,
        "rtt": 106.134,
        "playback_buffer_ratio": 0.9,
        "rebuffering_ratio": 0.02632852251086708,
        "playback_buffer_ratio_after": 1.1833333333333333,
        "rebuffering_ratio_after": 0.026188317094120048,
        "path_id": 1,
        "initial_explore": 0,
        "reward": 1.0
    },
    {
        "arm": 7,
        "seg_no": 192,
        "resolution": 1080,
        "bitrate": 87209.263,
        "bitrate_ratio": 1.0,
        "throughput": 27.24607461220692,
        "rtt": 19.534,
        "playback_buffer_ratio": 0.9875,
        "rebuffering_ratio": 0.026469146448504826,
        "playback_buffer_ratio_after": 1.3083333333333333,
        "rebuffering_ratio_after": 0.026188317094120048,
        "path_id": 2,
        "initial_explore": 0,
        "reward": 1.0
    },
    {
        "arm": 7,
        "seg_no": 191,
        "resolution": 1080,
        "bitrate": 87209.263,
        "bitrate_ratio": 1.0,
        "throughput": 106.74053224744162,
        "rtt": 105.626,
        "playback_buffer_ratio": 1.1791666666666667,
        "rebuffering_ratio": 0.026188317094120048,
        "playback_buffer_ratio_after": 1.2541666666666667,
        "rebuffering_ratio_after": 0.026188317094120048,
        "path_id": 1,
        "initial_explore": 0,
        "reward": 1.0
    },
    {
        "arm": 7,
        "seg_no": 193,
        "resolution": 1080,
        "bitrate": 87209.263,
        "bitrate_ratio": 1.0,
        "throughput": 27.505514201829783,
        "rtt": 19.616,
        "playback_buffer_ratio": 1.3083333333333333,
        "rebuffering_ratio": 0.026188317094120048,
        "playback_buffer_ratio_after": 1.2083333333333333,
        "rebuffering_ratio_after": 0.025912071208697346,
        "path_id": 2,
        "initial_explore": 0,
        "reward": 1.0
    },
    {
        "arm": 7,
        "seg_no": 194,
        "resolution": 1080,
        "bitrate": 87209.263,
        "bitrate_ratio": 1.0,
        "throughput": 67.47831680424754,
        "rtt": 105.908,
        "playback_buffer_ratio": 0.8,
        "rebuffering_ratio": 0.025510331725643792,
        "playback_buffer_ratio_after": 0.8125,
        "rebuffering_ratio_after": 0.025510331725643792,
        "path_id": 1,
        "initial_explore": 0,
        "reward": 1.0
    },
    {
        "arm": 7,
        "seg_no": 195,
        "resolution": 1080,
        "bitrate": 87209.263,
        "bitrate_ratio": 1.0,
        "throughput": 112.97008121047729,
        "rtt": 105.65,
        "playback_buffer_ratio": 0.8125,
        "rebuffering_ratio": 0.025510331725643792,
        "playback_buffer_ratio_after": 0.8916666666666667,
        "rebuffering_ratio_after": 0.02537978705553215,
        "path_id": 1,
        "initial_explore": 0,
        "reward": 1.0
    },
    {
        "arm": 7,
        "seg_no": 196,
        "resolution": 1080,
        "bitrate": 87209.263,
        "bitrate_ratio": 1.0,
        "throughput": 116.81140125093305,
        "rtt": 105.778,
        "playback_buffer_ratio": 0.8916666666666667,
        "rebuffering_ratio": 0.02537978705553215,
        "playback_buffer_ratio_after": 0.9666666666666667,
        "rebuffering_ratio_after": 0.025250501672533014,
        "path_id": 1,
        "initial_explore": 0,
        "reward": 1.0
    },
    {
        "arm": 7,
        "seg_no": 199,
        "resolution": 1080,
        "bitrate": 87209.263,
        "bitrate_ratio": 1.0,
        "throughput": 27.73918238278826,
        "rtt": 19.406,
        "playback_buffer_ratio": 0.9875,
        "rebuffering_ratio": 0.025510331725643792,
        "playback_buffer_ratio_after": 1.0625,
        "rebuffering_ratio_after": 0.025250501672533014,
        "path_id": 2,
        "initial_explore": 0,
        "reward": 1.0
    },
    {
        "arm": 7,
        "seg_no": 197,
        "resolution": 1080,
        "bitrate": 87209.263,
        "bitrate_ratio": 1.0,
        "throughput": 67.29402138692818,
        "rtt": 105.672,
        "playback_buffer_ratio": 0.9666666666666667,
        "rebuffering_ratio": 0.025250501672533014,
        "playback_buffer_ratio_after": 1.0041666666666667,
        "rebuffering_ratio_after": 0.025250501672533014,
        "path_id": 1,
        "initial_explore": 0,
        "reward": 1.0
    },
    {
        "arm": 7,
        "seg_no": 198,
        "resolution": 1080,
        "bitrate": 87209.263,
        "bitrate_ratio": 1.0,
        "throughput": 114.61469702120675,
        "rtt": 105.75,
        "playback_buffer_ratio": 1.0041666666666667,
        "rebuffering_ratio": 0.025250501672533014,
        "playback_buffer_ratio_after": 1.0708333333333333,
        "rebuffering_ratio_after": 0.025122511224554698,
        "path_id": 1,
        "initial_explore": 0,
        "reward": 1.0
    },
    {
        "arm": 7,
        "seg_no": 200,
        "resolution": 1080,
        "bitrate": 87209.263,
        "bitrate_ratio": 1.0,
        "throughput": 27.47818525751624,
        "rtt": 19.666,
        "playback_buffer_ratio": 1.0625,
        "rebuffering_ratio": 0.025250501672533014,
        "playback_buffer_ratio_after": 1.1041666666666667,
        "rebuffering_ratio_after": 0.02487008820049915,
        "path_id": 2,
        "initial_explore": 0,
        "reward": 1.0
    }
]