[
    {
        "start": 1682741589.4077237,
        "end": 1682741590.412615,
        "next_seg_no": 1,
        "completed": 1
    },
    {
        "start": 1682741610.6741312,
        "end": 1682741612.0551002,
        "next_seg_no": 11,
        "completed": 1
    },
    {
        "start": 1682741614.0781603,
        "end": 1682741620.6250694,
        "next_seg_no": 12,
        "completed": 1
    },
    {
        "start": 1682741626.6970654,
        "end": 1682741626.7684605,
        "next_seg_no": 15,
        "completed": 1
    },
    {
        "start": 1682742008.0838788,
        "end": 1682742008.083879,
        "next_seg_no": -1,
        "completed": 1
    }
]