[
    {
        "start": 1682762755.0265832,
        "end": 1682762755.5772843,
        "next_seg_no": 1,
        "completed": 1
    },
    {
        "start": 1682762773.7998226,
        "end": 1682762774.0474072,
        "next_seg_no": 10,
        "completed": 1
    },
    {
        "start": 1682762776.0671275,
        "end": 1682762779.0265129,
        "next_seg_no": 11,
        "completed": 1
    },
    {
        "start": 1682762781.0449774,
        "end": 1682762787.5914073,
        "next_seg_no": 12,
        "completed": 1
    },
    {
        "start": 1682762789.6091886,
        "end": 1682762791.2287424,
        "next_seg_no": 13,
        "completed": 1
    },
    {
        "start": 1682762793.2478747,
        "end": 1682762794.225452,
        "next_seg_no": 14,
        "completed": 1
    },
    {
        "start": 1682762796.2463143,
        "end": 1682762796.6129358,
        "next_seg_no": 15,
        "completed": 1
    },
    {
        "start": 1682762798.6350956,
        "end": 1682762799.8387861,
        "next_seg_no": 16,
        "completed": 1
    },
    {
        "start": 1682763177.0227318,
        "end": 1682763177.022732,
        "next_seg_no": -1,
        "completed": 1
    }
]