[
    {
        "start": 1681403803.3252935,
        "end": 1681403804.0650082,
        "next_seg_no": 1,
        "completed": 1
    },
    {
        "start": 1681403806.1217163,
        "end": 1681403807.636348,
        "next_seg_no": 2,
        "completed": 1
    },
    {
        "start": 1681403809.694203,
        "end": 1681403810.1994412,
        "next_seg_no": 3,
        "completed": 1
    },
    {
        "start": 1681403812.255258,
        "end": 1681403815.9957519,
        "next_seg_no": 4,
        "completed": 1
    },
    {
        "start": 1681403818.048265,
        "end": 1681403827.2205195,
        "next_seg_no": 5,
        "completed": 1
    },
    {
        "start": 1681403829.2689526,
        "end": 1681403831.0978901,
        "next_seg_no": 6,
        "completed": 1
    },
    {
        "start": 1681403839.295524,
        "end": 1681403841.103266,
        "next_seg_no": 10,
        "completed": 1
    },
    {
        "start": 1681403843.1525369,
        "end": 1681403846.3201303,
        "next_seg_no": 11,
        "completed": 1
    },
    {
        "start": 1681403848.3707945,
        "end": 1681403856.138352,
        "next_seg_no": 12,
        "completed": 1
    },
    {
        "start": 1681403858.1882417,
        "end": 1681403859.7876642,
        "next_seg_no": 13,
        "completed": 1
    },
    {
        "start": 1681403861.8314009,
        "end": 1681403862.9546657,
        "next_seg_no": 14,
        "completed": 1
    },
    {
        "start": 1681403865.0027192,
        "end": 1681403866.2437534,
        "next_seg_no": 15,
        "completed": 1
    },
    {
        "start": 1681403868.2943819,
        "end": 1681403869.6102734,
        "next_seg_no": 16,
        "completed": 1
    },
    {
        "start": 1681403871.6574967,
        "end": 1681403872.608284,
        "next_seg_no": 17,
        "completed": 1
    },
    {
        "start": 1681403874.6535916,
        "end": 1681403875.026483,
        "next_seg_no": 18,
        "completed": 1
    },
    {
        "start": 1681403877.0810814,
        "end": 1681403877.1953557,
        "next_seg_no": 19,
        "completed": 1
    },
    {
        "start": 1681403893.599763,
        "end": 1681403921.3003604,
        "next_seg_no": 27,
        "completed": 1
    },
    {
        "start": 1681403923.3540614,
        "end": 1681403923.6580558,
        "next_seg_no": 28,
        "completed": 1
    },
    {
        "start": 1681403987.812131,
        "end": 1681404007.6887176,
        "next_seg_no": 59,
        "completed": 1
    },
    {
        "start": 1681404009.7341533,
        "end": 1681404010.1445584,
        "next_seg_no": 60,
        "completed": 1
    },
    {
        "start": 1681404045.299899,
        "end": 1681404063.492057,
        "next_seg_no": 77,
        "completed": 1
    },
    {
        "start": 1681404111.3186371,
        "end": 1681404125.2408066,
        "next_seg_no": 100,
        "completed": 1
    },
    {
        "start": 1681404127.2911518,
        "end": 1681404142.2671435,
        "next_seg_no": 101,
        "completed": 1
    },
    {
        "start": 1681404144.3183963,
        "end": 1681404172.2694294,
        "next_seg_no": 102,
        "completed": 1
    },
    {
        "start": 1681404222.0153468,
        "end": 1681404242.2980843,
        "next_seg_no": 126,
        "completed": 1
    },
    {
        "start": 1681404246.40211,
        "end": 1681404272.7211416,
        "next_seg_no": 128,
        "completed": 1
    },
    {
        "start": 1681404332.872473,
        "end": 1681404352.8896837,
        "next_seg_no": 157,
        "completed": 1
    },
    {
        "start": 1681404384.009032,
        "end": 1681404390.2317224,
        "next_seg_no": 172,
        "completed": 1
    },
    {
        "start": 1681404392.285916,
        "end": 1681404392.529863,
        "next_seg_no": 173,
        "completed": 1
    },
    {
        "start": 1681404394.614164,
        "end": 1681404394.8857965,
        "next_seg_no": 174,
        "completed": 1
    },
    {
        "start": 1681404423.9245546,
        "end": 1681404426.1474688,
        "next_seg_no": 188,
        "completed": 1
    },
    {
        "start": 1681404453.58163,
        "end": 1681404453.5816305,
        "next_seg_no": -1,
        "completed": 1
    }
]